Encoder/freq_div.v
module freq_div(
    input wire clock,
    output reg div_clk
);
  
  integer count = 0;
  
  always @(posedge clock)
    begin
      if(count != 100)
        begin
          div_clk = 0;
        end
      else
        begin
          count = 0;
          div_clk = 1;
        end
      
      count = count + 1;
    end
endmodule

Encoder/Div/freq_div_tb.v
module freq_div_tb;
  reg clock;
  wire div_clk;
  integer i;
  
  freq_div uut(
    .clock(clock),
    .div_clk(div_clk));
  
  initial begin
    $dumpfile("freq_div_tb.vcd");
    $dumpvars(0,freq_div_tb);
    
    clock = 1;
  end
  
  initial begin
    for(i = 0; i < 5000; i = i+1) begin
          #5 clock <= ~clock;
    end
  end
endmodule

Encoder/Div/freq_div_tb.vcd
$date
	Thu May 12 22:13:11 2022
$end
$version
	Icarus Verilog
$end
$timescale
	1s
$end
$scope module freq_div_tb $end
$var wire 1 ! div_clk $end
$var reg 1 " clock $end
$var integer 32 # i [31:0] $end
$scope module uut $end
$var wire 1 " clock $end
$var reg 1 ! div_clk $end
$var integer 32 $ count [31:0] $end
$upscope $end
$upscope $end
$enddefinitions $end
#0
$dumpvars
b1 $
b0 #
1"
0!
$end
#5
0"
b1 #
#10
b10 $
1"
b10 #
#15
0"
b11 #
#20
b11 $
1"
b100 #
#25
0"
b101 #
#30
b100 $
1"
b110 #
#35
0"
b111 #
#40
b101 $
1"
b1000 #
#45
0"
b1001 #
#50
b110 $
1"
b1010 #
#55
0"
b1011 #
#60
b111 $
1"
b1100 #
#65
0"
b1101 #
#70
b1000 $
1"
b1110 #
#75
0"
b1111 #
#80
b1001 $
1"
b10000 #
#85
0"
b10001 #
#90
b1010 $
1"
b10010 #
#95
0"
b10011 #
#100
b1011 $
1"
b10100 #
#105
0"
b10101 #
#110
b1100 $
1"
b10110 #
#115
0"
b10111 #
#120
b1101 $
1"
b11000 #
#125
0"
b11001 #
#130
b1110 $
1"
b11010 #
#135
0"
b11011 #
#140
b1111 $
1"
b11100 #
#145
0"
b11101 #
#150
b10000 $
1"
b11110 #
#155
0"
b11111 #
#160
b10001 $
1"
b100000 #
#165
0"
b100001 #
#170
b10010 $
1"
b100010 #
#175
0"
b100011 #
#180
b10011 $
1"
b100100 #
#185
0"
b100101 #
#190
b10100 $
1"
b100110 #
#195
0"
b100111 #
#200
b10101 $
1"
b101000 #
#205
0"
b101001 #
#210
b10110 $
1"
b101010 #
#215
0"
b101011 #
#220
b10111 $
1"
b101100 #
#225
0"
b101101 #
#230
b11000 $
1"
b101110 #
#235
0"
b101111 #
#240
b11001 $
1"
b110000 #
#245
0"
b110001 #
#250
b11010 $
1"
b110010 #
#255
0"
b110011 #
#260
b11011 $
1"
b110100 #
#265
0"
b110101 #
#270
b11100 $
1"
b110110 #
#275
0"
b110111 #
#280
b11101 $
1"
b111000 #
#285
0"
b111001 #
#290
b11110 $
1"
b111010 #
#295
0"
b111011 #
#300
b11111 $
1"
b111100 #
#305
0"
b111101 #
#310
b100000 $
1"
b111110 #
#315
0"
b111111 #
#320
b100001 $
1"
b1000000 #
#325
0"
b1000001 #
#330
b100010 $
1"
b1000010 #
#335
0"
b1000011 #
#340
b100011 $
1"
b1000100 #
#345
0"
b1000101 #
#350
b100100 $
1"
b1000110 #
#355
0"
b1000111 #
#360
b100101 $
1"
b1001000 #
#365
0"
b1001001 #
#370
b100110 $
1"
b1001010 #
#375
0"
b1001011 #
#380
b100111 $
1"
b1001100 #
#385
0"
b1001101 #
#390
b101000 $
1"
b1001110 #
#395
0"
b1001111 #
#400
b101001 $
1"
b1010000 #
#405
0"
b1010001 #
#410
b101010 $
1"
b1010010 #
#415
0"
b1010011 #
#420
b101011 $
1"
b1010100 #
#425
0"
b1010101 #
#430
b101100 $
1"
b1010110 #
#435
0"
b1010111 #
#440
b101101 $
1"
b1011000 #
#445
0"
b1011001 #
#450
b101110 $
1"
b1011010 #
#455
0"
b1011011 #
#460
b101111 $
1"
b1011100 #
#465
0"
b1011101 #
#470
b110000 $
1"
b1011110 #
#475
0"
b1011111 #
#480
b110001 $
1"
b1100000 #
#485
0"
b1100001 #
#490
b110010 $
1"
b1100010 #
#495
0"
b1100011 #
#500
b110011 $
1"
b1100100 #
#505
0"
b1100101 #
#510
b110100 $
1"
b1100110 #
#515
0"
b1100111 #
#520
b110101 $
1"
b1101000 #
#525
0"
b1101001 #
#530
b110110 $
1"
b1101010 #
#535
0"
b1101011 #
#540
b110111 $
1"
b1101100 #
#545
0"
b1101101 #
#550
b111000 $
1"
b1101110 #
#555
0"
b1101111 #
#560
b111001 $
1"
b1110000 #
#565
0"
b1110001 #
#570
b111010 $
1"
b1110010 #
#575
0"
b1110011 #
#580
b111011 $
1"
b1110100 #
#585
0"
b1110101 #
#590
b111100 $
1"
b1110110 #
#595
0"
b1110111 #
#600
b111101 $
1"
b1111000 #
#605
0"
b1111001 #
#610
b111110 $
1"
b1111010 #
#615
0"
b1111011 #
#620
b111111 $
1"
b1111100 #
#625
0"
b1111101 #
#630
b1000000 $
1"
b1111110 #
#635
0"
b1111111 #
#640
b1000001 $
1"
b10000000 #
#645
0"
b10000001 #
#650
b1000010 $
1"
b10000010 #
#655
0"
b10000011 #
#660
b1000011 $
1"
b10000100 #
#665
0"
b10000101 #
#670
b1000100 $
1"
b10000110 #
#675
0"
b10000111 #
#680
b1000101 $
1"
b10001000 #
#685
0"
b10001001 #
#690
b1000110 $
1"
b10001010 #
#695
0"
b10001011 #
#700
b1000111 $
1"
b10001100 #
#705
0"
b10001101 #
#710
b1001000 $
1"
b10001110 #
#715
0"
b10001111 #
#720
b1001001 $
1"
b10010000 #
#725
0"
b10010001 #
#730
b1001010 $
1"
b10010010 #
#735
0"
b10010011 #
#740
b1001011 $
1"
b10010100 #
#745
0"
b10010101 #
#750
b1001100 $
1"
b10010110 #
#755
0"
b10010111 #
#760
b1001101 $
1"
b10011000 #
#765
0"
b10011001 #
#770
b1001110 $
1"
b10011010 #
#775
0"
b10011011 #
#780
b1001111 $
1"
b10011100 #
#785
0"
b10011101 #
#790
b1010000 $
1"
b10011110 #
#795
0"
b10011111 #
#800
b1010001 $
1"
b10100000 #
#805
0"
b10100001 #
#810
b1010010 $
1"
b10100010 #
#815
0"
b10100011 #
#820
b1010011 $
1"
b10100100 #
#825
0"
b10100101 #
#830
b1010100 $
1"
b10100110 #
#835
0"
b10100111 #
#840
b1010101 $
1"
b10101000 #
#845
0"
b10101001 #
#850
b1010110 $
1"
b10101010 #
#855
0"
b10101011 #
#860
b1010111 $
1"
b10101100 #
#865
0"
b10101101 #
#870
b1011000 $
1"
b10101110 #
#875
0"
b10101111 #
#880
b1011001 $
1"
b10110000 #
#885
0"
b10110001 #
#890
b1011010 $
1"
b10110010 #
#895
0"
b10110011 #
#900
b1011011 $
1"
b10110100 #
#905
0"
b10110101 #
#910
b1011100 $
1"
b10110110 #
#915
0"
b10110111 #
#920
b1011101 $
1"
b10111000 #
#925
0"
b10111001 #
#930
b1011110 $
1"
b10111010 #
#935
0"
b10111011 #
#940
b1011111 $
1"
b10111100 #
#945
0"
b10111101 #
#950
b1100000 $
1"
b10111110 #
#955
0"
b10111111 #
#960
b1100001 $
1"
b11000000 #
#965
0"
b11000001 #
#970
b1100010 $
1"
b11000010 #
#975
0"
b11000011 #
#980
b1100011 $
1"
b11000100 #
#985
0"
b11000101 #
#990
b1100100 $
1"
b11000110 #
#995
0"
b11000111 #
#1000
1!
b1 $
1"
b11001000 #
#1005
0"
b11001001 #
#1010
b10 $
0!
1"
b11001010 #
#1015
0"
b11001011 #
#1020
b11 $
1"
b11001100 #
#1025
0"
b11001101 #
#1030
b100 $
1"
b11001110 #
#1035
0"
b11001111 #
#1040
b101 $
1"
b11010000 #
#1045
0"
b11010001 #
#1050
b110 $
1"
b11010010 #
#1055
0"
b11010011 #
#1060
b111 $
1"
b11010100 #
#1065
0"
b11010101 #
#1070
b1000 $
1"
b11010110 #
#1075
0"
b11010111 #
#1080
b1001 $
1"
b11011000 #
#1085
0"
b11011001 #
#1090
b1010 $
1"
b11011010 #
#1095
0"
b11011011 #
#1100
b1011 $
1"
b11011100 #
#1105
0"
b11011101 #
#1110
b1100 $
1"
b11011110 #
#1115
0"
b11011111 #
#1120
b1101 $
1"
b11100000 #
#1125
0"
b11100001 #
#1130
b1110 $
1"
b11100010 #
#1135
0"
b11100011 #
#1140
b1111 $
1"
b11100100 #
#1145
0"
b11100101 #
#1150
b10000 $
1"
b11100110 #
#1155
0"
b11100111 #
#1160
b10001 $
1"
b11101000 #
#1165
0"
b11101001 #
#1170
b10010 $
1"
b11101010 #
#1175
0"
b11101011 #
#1180
b10011 $
1"
b11101100 #
#1185
0"
b11101101 #
#1190
b10100 $
1"
b11101110 #
#1195
0"
b11101111 #
#1200
b10101 $
1"
b11110000 #
#1205
0"
b11110001 #
#1210
b10110 $
1"
b11110010 #
#1215
0"
b11110011 #
#1220
b10111 $
1"
b11110100 #
#1225
0"
b11110101 #
#1230
b11000 $
1"
b11110110 #
#1235
0"
b11110111 #
#1240
b11001 $
1"
b11111000 #
#1245
0"
b11111001 #
#1250
b11010 $
1"
b11111010 #
#1255
0"
b11111011 #
#1260
b11011 $
1"
b11111100 #
#1265
0"
b11111101 #
#1270
b11100 $
1"
b11111110 #
#1275
0"
b11111111 #
#1280
b11101 $
1"
b100000000 #
#1285
0"
b100000001 #
#1290
b11110 $
1"
b100000010 #
#1295
0"
b100000011 #
#1300
b11111 $
1"
b100000100 #
#1305
0"
b100000101 #
#1310
b100000 $
1"
b100000110 #
#1315
0"
b100000111 #
#1320
b100001 $
1"
b100001000 #
#1325
0"
b100001001 #
#1330
b100010 $
1"
b100001010 #
#1335
0"
b100001011 #
#1340
b100011 $
1"
b100001100 #
#1345
0"
b100001101 #
#1350
b100100 $
1"
b100001110 #
#1355
0"
b100001111 #
#1360
b100101 $
1"
b100010000 #
#1365
0"
b100010001 #
#1370
b100110 $
1"
b100010010 #
#1375
0"
b100010011 #
#1380
b100111 $
1"
b100010100 #
#1385
0"
b100010101 #
#1390
b101000 $
1"
b100010110 #
#1395
0"
b100010111 #
#1400
b101001 $
1"
b100011000 #
#1405
0"
b100011001 #
#1410
b101010 $
1"
b100011010 #
#1415
0"
b100011011 #
#1420
b101011 $
1"
b100011100 #
#1425
0"
b100011101 #
#1430
b101100 $
1"
b100011110 #
#1435
0"
b100011111 #
#1440
b101101 $
1"
b100100000 #
#1445
0"
b100100001 #
#1450
b101110 $
1"
b100100010 #
#1455
0"
b100100011 #
#1460
b101111 $
1"
b100100100 #
#1465
0"
b100100101 #
#1470
b110000 $
1"
b100100110 #
#1475
0"
b100100111 #
#1480
b110001 $
1"
b100101000 #
#1485
0"
b100101001 #
#1490
b110010 $
1"
b100101010 #
#1495
0"
b100101011 #
#1500
b110011 $
1"
b100101100 #
#1505
0"
b100101101 #
#1510
b110100 $
1"
b100101110 #
#1515
0"
b100101111 #
#1520
b110101 $
1"
b100110000 #
#1525
0"
b100110001 #
#1530
b110110 $
1"
b100110010 #
#1535
0"
b100110011 #
#1540
b110111 $
1"
b100110100 #
#1545
0"
b100110101 #
#1550
b111000 $
1"
b100110110 #
#1555
0"
b100110111 #
#1560
b111001 $
1"
b100111000 #
#1565
0"
b100111001 #
#1570
b111010 $
1"
b100111010 #
#1575
0"
b100111011 #
#1580
b111011 $
1"
b100111100 #
#1585
0"
b100111101 #
#1590
b111100 $
1"
b100111110 #
#1595
0"
b100111111 #
#1600
b111101 $
1"
b101000000 #
#1605
0"
b101000001 #
#1610
b111110 $
1"
b101000010 #
#1615
0"
b101000011 #
#1620
b111111 $
1"
b101000100 #
#1625
0"
b101000101 #
#1630
b1000000 $
1"
b101000110 #
#1635
0"
b101000111 #
#1640
b1000001 $
1"
b101001000 #
#1645
0"
b101001001 #
#1650
b1000010 $
1"
b101001010 #
#1655
0"
b101001011 #
#1660
b1000011 $
1"
b101001100 #
#1665
0"
b101001101 #
#1670
b1000100 $
1"
b101001110 #
#1675
0"
b101001111 #
#1680
b1000101 $
1"
b101010000 #
#1685
0"
b101010001 #
#1690
b1000110 $
1"
b101010010 #
#1695
0"
b101010011 #
#1700
b1000111 $
1"
b101010100 #
#1705
0"
b101010101 #
#1710
b1001000 $
1"
b101010110 #
#1715
0"
b101010111 #
#1720
b1001001 $
1"
b101011000 #
#1725
0"
b101011001 #
#1730
b1001010 $
1"
b101011010 #
#1735
0"
b101011011 #
#1740
b1001011 $
1"
b101011100 #
#1745
0"
b101011101 #
#1750
b1001100 $
1"
b101011110 #
#1755
0"
b101011111 #
#1760
b1001101 $
1"
b101100000 #
#1765
0"
b101100001 #
#1770
b1001110 $
1"
b101100010 #
#1775
0"
b101100011 #
#1780
b1001111 $
1"
b101100100 #
#1785
0"
b101100101 #
#1790
b1010000 $
1"
b101100110 #
#1795
0"
b101100111 #
#1800
b1010001 $
1"
b101101000 #
#1805
0"
b101101001 #
#1810
b1010010 $
1"
b101101010 #
#1815
0"
b101101011 #
#1820
b1010011 $
1"
b101101100 #
#1825
0"
b101101101 #
#1830
b1010100 $
1"
b101101110 #
#1835
0"
b101101111 #
#1840
b1010101 $
1"
b101110000 #
#1845
0"
b101110001 #
#1850
b1010110 $
1"
b101110010 #
#1855
0"
b101110011 #
#1860
b1010111 $
1"
b101110100 #
#1865
0"
b101110101 #
#1870
b1011000 $
1"
b101110110 #
#1875
0"
b101110111 #
#1880
b1011001 $
1"
b101111000 #
#1885
0"
b101111001 #
#1890
b1011010 $
1"
b101111010 #
#1895
0"
b101111011 #
#1900
b1011011 $
1"
b101111100 #
#1905
0"
b101111101 #
#1910
b1011100 $
1"
b101111110 #
#1915
0"
b101111111 #
#1920
b1011101 $
1"
b110000000 #
#1925
0"
b110000001 #
#1930
b1011110 $
1"
b110000010 #
#1935
0"
b110000011 #
#1940
b1011111 $
1"
b110000100 #
#1945
0"
b110000101 #
#1950
b1100000 $
1"
b110000110 #
#1955
0"
b110000111 #
#1960
b1100001 $
1"
b110001000 #
#1965
0"
b110001001 #
#1970
b1100010 $
1"
b110001010 #
#1975
0"
b110001011 #
#1980
b1100011 $
1"
b110001100 #
#1985
0"
b110001101 #
#1990
b1100100 $
1"
b110001110 #
#1995
0"
b110001111 #
#2000
1!
b1 $
1"
b110010000 #
#2005
0"
b110010001 #
#2010
b10 $
0!
1"
b110010010 #
#2015
0"
b110010011 #
#2020
b11 $
1"
b110010100 #
#2025
0"
b110010101 #
#2030
b100 $
1"
b110010110 #
#2035
0"
b110010111 #
#2040
b101 $
1"
b110011000 #
#2045
0"
b110011001 #
#2050
b110 $
1"
b110011010 #
#2055
0"
b110011011 #
#2060
b111 $
1"
b110011100 #
#2065
0"
b110011101 #
#2070
b1000 $
1"
b110011110 #
#2075
0"
b110011111 #
#2080
b1001 $
1"
b110100000 #
#2085
0"
b110100001 #
#2090
b1010 $
1"
b110100010 #
#2095
0"
b110100011 #
#2100
b1011 $
1"
b110100100 #
#2105
0"
b110100101 #
#2110
b1100 $
1"
b110100110 #
#2115
0"
b110100111 #
#2120
b1101 $
1"
b110101000 #
#2125
0"
b110101001 #
#2130
b1110 $
1"
b110101010 #
#2135
0"
b110101011 #
#2140
b1111 $
1"
b110101100 #
#2145
0"
b110101101 #
#2150
b10000 $
1"
b110101110 #
#2155
0"
b110101111 #
#2160
b10001 $
1"
b110110000 #
#2165
0"
b110110001 #
#2170
b10010 $
1"
b110110010 #
#2175
0"
b110110011 #
#2180
b10011 $
1"
b110110100 #
#2185
0"
b110110101 #
#2190
b10100 $
1"
b110110110 #
#2195
0"
b110110111 #
#2200
b10101 $
1"
b110111000 #
#2205
0"
b110111001 #
#2210
b10110 $
1"
b110111010 #
#2215
0"
b110111011 #
#2220
b10111 $
1"
b110111100 #
#2225
0"
b110111101 #
#2230
b11000 $
1"
b110111110 #
#2235
0"
b110111111 #
#2240
b11001 $
1"
b111000000 #
#2245
0"
b111000001 #
#2250
b11010 $
1"
b111000010 #
#2255
0"
b111000011 #
#2260
b11011 $
1"
b111000100 #
#2265
0"
b111000101 #
#2270
b11100 $
1"
b111000110 #
#2275
0"
b111000111 #
#2280
b11101 $
1"
b111001000 #
#2285
0"
b111001001 #
#2290
b11110 $
1"
b111001010 #
#2295
0"
b111001011 #
#2300
b11111 $
1"
b111001100 #
#2305
0"
b111001101 #
#2310
b100000 $
1"
b111001110 #
#2315
0"
b111001111 #
#2320
b100001 $
1"
b111010000 #
#2325
0"
b111010001 #
#2330
b100010 $
1"
b111010010 #
#2335
0"
b111010011 #
#2340
b100011 $
1"
b111010100 #
#2345
0"
b111010101 #
#2350
b100100 $
1"
b111010110 #
#2355
0"
b111010111 #
#2360
b100101 $
1"
b111011000 #
#2365
0"
b111011001 #
#2370
b100110 $
1"
b111011010 #
#2375
0"
b111011011 #
#2380
b100111 $
1"
b111011100 #
#2385
0"
b111011101 #
#2390
b101000 $
1"
b111011110 #
#2395
0"
b111011111 #
#2400
b101001 $
1"
b111100000 #
#2405
0"
b111100001 #
#2410
b101010 $
1"
b111100010 #
#2415
0"
b111100011 #
#2420
b101011 $
1"
b111100100 #
#2425
0"
b111100101 #
#2430
b101100 $
1"
b111100110 #
#2435
0"
b111100111 #
#2440
b101101 $
1"
b111101000 #
#2445
0"
b111101001 #
#2450
b101110 $
1"
b111101010 #
#2455
0"
b111101011 #
#2460
b101111 $
1"
b111101100 #
#2465
0"
b111101101 #
#2470
b110000 $
1"
b111101110 #
#2475
0"
b111101111 #
#2480
b110001 $
1"
b111110000 #
#2485
0"
b111110001 #
#2490
b110010 $
1"
b111110010 #
#2495
0"
b111110011 #
#2500
b110011 $
1"
b111110100 #
#2505
0"
b111110101 #
#2510
b110100 $
1"
b111110110 #
#2515
0"
b111110111 #
#2520
b110101 $
1"
b111111000 #
#2525
0"
b111111001 #
#2530
b110110 $
1"
b111111010 #
#2535
0"
b111111011 #
#2540
b110111 $
1"
b111111100 #
#2545
0"
b111111101 #
#2550
b111000 $
1"
b111111110 #
#2555
0"
b111111111 #
#2560
b111001 $
1"
b1000000000 #
#2565
0"
b1000000001 #
#2570
b111010 $
1"
b1000000010 #
#2575
0"
b1000000011 #
#2580
b111011 $
1"
b1000000100 #
#2585
0"
b1000000101 #
#2590
b111100 $
1"
b1000000110 #
#2595
0"
b1000000111 #
#2600
b111101 $
1"
b1000001000 #
#2605
0"
b1000001001 #
#2610
b111110 $
1"
b1000001010 #
#2615
0"
b1000001011 #
#2620
b111111 $
1"
b1000001100 #
#2625
0"
b1000001101 #
#2630
b1000000 $
1"
b1000001110 #
#2635
0"
b1000001111 #
#2640
b1000001 $
1"
b1000010000 #
#2645
0"
b1000010001 #
#2650
b1000010 $
1"
b1000010010 #
#2655
0"
b1000010011 #
#2660
b1000011 $
1"
b1000010100 #
#2665
0"
b1000010101 #
#2670
b1000100 $
1"
b1000010110 #
#2675
0"
b1000010111 #
#2680
b1000101 $
1"
b1000011000 #
#2685
0"
b1000011001 #
#2690
b1000110 $
1"
b1000011010 #
#2695
0"
b1000011011 #
#2700
b1000111 $
1"
b1000011100 #
#2705
0"
b1000011101 #
#2710
b1001000 $
1"
b1000011110 #
#2715
0"
b1000011111 #
#2720
b1001001 $
1"
b1000100000 #
#2725
0"
b1000100001 #
#2730
b1001010 $
1"
b1000100010 #
#2735
0"
b1000100011 #
#2740
b1001011 $
1"
b1000100100 #
#2745
0"
b1000100101 #
#2750
b1001100 $
1"
b1000100110 #
#2755
0"
b1000100111 #
#2760
b1001101 $
1"
b1000101000 #
#2765
0"
b1000101001 #
#2770
b1001110 $
1"
b1000101010 #
#2775
0"
b1000101011 #
#2780
b1001111 $
1"
b1000101100 #
#2785
0"
b1000101101 #
#2790
b1010000 $
1"
b1000101110 #
#2795
0"
b1000101111 #
#2800
b1010001 $
1"
b1000110000 #
#2805
0"
b1000110001 #
#2810
b1010010 $
1"
b1000110010 #
#2815
0"
b1000110011 #
#2820
b1010011 $
1"
b1000110100 #
#2825
0"
b1000110101 #
#2830
b1010100 $
1"
b1000110110 #
#2835
0"
b1000110111 #
#2840
b1010101 $
1"
b1000111000 #
#2845
0"
b1000111001 #
#2850
b1010110 $
1"
b1000111010 #
#2855
0"
b1000111011 #
#2860
b1010111 $
1"
b1000111100 #
#2865
0"
b1000111101 #
#2870
b1011000 $
1"
b1000111110 #
#2875
0"
b1000111111 #
#2880
b1011001 $
1"
b1001000000 #
#2885
0"
b1001000001 #
#2890
b1011010 $
1"
b1001000010 #
#2895
0"
b1001000011 #
#2900
b1011011 $
1"
b1001000100 #
#2905
0"
b1001000101 #
#2910
b1011100 $
1"
b1001000110 #
#2915
0"
b1001000111 #
#2920
b1011101 $
1"
b1001001000 #
#2925
0"
b1001001001 #
#2930
b1011110 $
1"
b1001001010 #
#2935
0"
b1001001011 #
#2940
b1011111 $
1"
b1001001100 #
#2945
0"
b1001001101 #
#2950
b1100000 $
1"
b1001001110 #
#2955
0"
b1001001111 #
#2960
b1100001 $
1"
b1001010000 #
#2965
0"
b1001010001 #
#2970
b1100010 $
1"
b1001010010 #
#2975
0"
b1001010011 #
#2980
b1100011 $
1"
b1001010100 #
#2985
0"
b1001010101 #
#2990
b1100100 $
1"
b1001010110 #
#2995
0"
b1001010111 #
#3000
1!
b1 $
1"
b1001011000 #
#3005
0"
b1001011001 #
#3010
b10 $
0!
1"
b1001011010 #
#3015
0"
b1001011011 #
#3020
b11 $
1"
b1001011100 #
#3025
0"
b1001011101 #
#3030
b100 $
1"
b1001011110 #
#3035
0"
b1001011111 #
#3040
b101 $
1"
b1001100000 #
#3045
0"
b1001100001 #
#3050
b110 $
1"
b1001100010 #
#3055
0"
b1001100011 #
#3060
b111 $
1"
b1001100100 #
#3065
0"
b1001100101 #
#3070
b1000 $
1"
b1001100110 #
#3075
0"
b1001100111 #
#3080
b1001 $
1"
b1001101000 #
#3085
0"
b1001101001 #
#3090
b1010 $
1"
b1001101010 #
#3095
0"
b1001101011 #
#3100
b1011 $
1"
b1001101100 #
#3105
0"
b1001101101 #
#3110
b1100 $
1"
b1001101110 #
#3115
0"
b1001101111 #
#3120
b1101 $
1"
b1001110000 #
#3125
0"
b1001110001 #
#3130
b1110 $
1"
b1001110010 #
#3135
0"
b1001110011 #
#3140
b1111 $
1"
b1001110100 #
#3145
0"
b1001110101 #
#3150
b10000 $
1"
b1001110110 #
#3155
0"
b1001110111 #
#3160
b10001 $
1"
b1001111000 #
#3165
0"
b1001111001 #
#3170
b10010 $
1"
b1001111010 #
#3175
0"
b1001111011 #
#3180
b10011 $
1"
b1001111100 #
#3185
0"
b1001111101 #
#3190
b10100 $
1"
b1001111110 #
#3195
0"
b1001111111 #
#3200
b10101 $
1"
b1010000000 #
#3205
0"
b1010000001 #
#3210
b10110 $
1"
b1010000010 #
#3215
0"
b1010000011 #
#3220
b10111 $
1"
b1010000100 #
#3225
0"
b1010000101 #
#3230
b11000 $
1"
b1010000110 #
#3235
0"
b1010000111 #
#3240
b11001 $
1"
b1010001000 #
#3245
0"
b1010001001 #
#3250
b11010 $
1"
b1010001010 #
#3255
0"
b1010001011 #
#3260
b11011 $
1"
b1010001100 #
#3265
0"
b1010001101 #
#3270
b11100 $
1"
b1010001110 #
#3275
0"
b1010001111 #
#3280
b11101 $
1"
b1010010000 #
#3285
0"
b1010010001 #
#3290
b11110 $
1"
b1010010010 #
#3295
0"
b1010010011 #
#3300
b11111 $
1"
b1010010100 #
#3305
0"
b1010010101 #
#3310
b100000 $
1"
b1010010110 #
#3315
0"
b1010010111 #
#3320
b100001 $
1"
b1010011000 #
#3325
0"
b1010011001 #
#3330
b100010 $
1"
b1010011010 #
#3335
0"
b1010011011 #
#3340
b100011 $
1"
b1010011100 #
#3345
0"
b1010011101 #
#3350
b100100 $
1"
b1010011110 #
#3355
0"
b1010011111 #
#3360
b100101 $
1"
b1010100000 #
#3365
0"
b1010100001 #
#3370
b100110 $
1"
b1010100010 #
#3375
0"
b1010100011 #
#3380
b100111 $
1"
b1010100100 #
#3385
0"
b1010100101 #
#3390
b101000 $
1"
b1010100110 #
#3395
0"
b1010100111 #
#3400
b101001 $
1"
b1010101000 #
#3405
0"
b1010101001 #
#3410
b101010 $
1"
b1010101010 #
#3415
0"
b1010101011 #
#3420
b101011 $
1"
b1010101100 #
#3425
0"
b1010101101 #
#3430
b101100 $
1"
b1010101110 #
#3435
0"
b1010101111 #
#3440
b101101 $
1"
b1010110000 #
#3445
0"
b1010110001 #
#3450
b101110 $
1"
b1010110010 #
#3455
0"
b1010110011 #
#3460
b101111 $
1"
b1010110100 #
#3465
0"
b1010110101 #
#3470
b110000 $
1"
b1010110110 #
#3475
0"
b1010110111 #
#3480
b110001 $
1"
b1010111000 #
#3485
0"
b1010111001 #
#3490
b110010 $
1"
b1010111010 #
#3495
0"
b1010111011 #
#3500
b110011 $
1"
b1010111100 #
#3505
0"
b1010111101 #
#3510
b110100 $
1"
b1010111110 #
#3515
0"
b1010111111 #
#3520
b110101 $
1"
b1011000000 #
#3525
0"
b1011000001 #
#3530
b110110 $
1"
b1011000010 #
#3535
0"
b1011000011 #
#3540
b110111 $
1"
b1011000100 #
#3545
0"
b1011000101 #
#3550
b111000 $
1"
b1011000110 #
#3555
0"
b1011000111 #
#3560
b111001 $
1"
b1011001000 #
#3565
0"
b1011001001 #
#3570
b111010 $
1"
b1011001010 #
#3575
0"
b1011001011 #
#3580
b111011 $
1"
b1011001100 #
#3585
0"
b1011001101 #
#3590
b111100 $
1"
b1011001110 #
#3595
0"
b1011001111 #
#3600
b111101 $
1"
b1011010000 #
#3605
0"
b1011010001 #
#3610
b111110 $
1"
b1011010010 #
#3615
0"
b1011010011 #
#3620
b111111 $
1"
b1011010100 #
#3625
0"
b1011010101 #
#3630
b1000000 $
1"
b1011010110 #
#3635
0"
b1011010111 #
#3640
b1000001 $
1"
b1011011000 #
#3645
0"
b1011011001 #
#3650
b1000010 $
1"
b1011011010 #
#3655
0"
b1011011011 #
#3660
b1000011 $
1"
b1011011100 #
#3665
0"
b1011011101 #
#3670
b1000100 $
1"
b1011011110 #
#3675
0"
b1011011111 #
#3680
b1000101 $
1"
b1011100000 #
#3685
0"
b1011100001 #
#3690
b1000110 $
1"
b1011100010 #
#3695
0"
b1011100011 #
#3700
b1000111 $
1"
b1011100100 #
#3705
0"
b1011100101 #
#3710
b1001000 $
1"
b1011100110 #
#3715
0"
b1011100111 #
#3720
b1001001 $
1"
b1011101000 #
#3725
0"
b1011101001 #
#3730
b1001010 $
1"
b1011101010 #
#3735
0"
b1011101011 #
#3740
b1001011 $
1"
b1011101100 #
#3745
0"
b1011101101 #
#3750
b1001100 $
1"
b1011101110 #
#3755
0"
b1011101111 #
#3760
b1001101 $
1"
b1011110000 #
#3765
0"
b1011110001 #
#3770
b1001110 $
1"
b1011110010 #
#3775
0"
b1011110011 #
#3780
b1001111 $
1"
b1011110100 #
#3785
0"
b1011110101 #
#3790
b1010000 $
1"
b1011110110 #
#3795
0"
b1011110111 #
#3800
b1010001 $
1"
b1011111000 #
#3805
0"
b1011111001 #
#3810
b1010010 $
1"
b1011111010 #
#3815
0"
b1011111011 #
#3820
b1010011 $
1"
b1011111100 #
#3825
0"
b1011111101 #
#3830
b1010100 $
1"
b1011111110 #
#3835
0"
b1011111111 #
#3840
b1010101 $
1"
b1100000000 #
#3845
0"
b1100000001 #
#3850
b1010110 $
1"
b1100000010 #
#3855
0"
b1100000011 #
#3860
b1010111 $
1"
b1100000100 #
#3865
0"
b1100000101 #
#3870
b1011000 $
1"
b1100000110 #
#3875
0"
b1100000111 #
#3880
b1011001 $
1"
b1100001000 #
#3885
0"
b1100001001 #
#3890
b1011010 $
1"
b1100001010 #
#3895
0"
b1100001011 #
#3900
b1011011 $
1"
b1100001100 #
#3905
0"
b1100001101 #
#3910
b1011100 $
1"
b1100001110 #
#3915
0"
b1100001111 #
#3920
b1011101 $
1"
b1100010000 #
#3925
0"
b1100010001 #
#3930
b1011110 $
1"
b1100010010 #
#3935
0"
b1100010011 #
#3940
b1011111 $
1"
b1100010100 #
#3945
0"
b1100010101 #
#3950
b1100000 $
1"
b1100010110 #
#3955
0"
b1100010111 #
#3960
b1100001 $
1"
b1100011000 #
#3965
0"
b1100011001 #
#3970
b1100010 $
1"
b1100011010 #
#3975
0"
b1100011011 #
#3980
b1100011 $
1"
b1100011100 #
#3985
0"
b1100011101 #
#3990
b1100100 $
1"
b1100011110 #
#3995
0"
b1100011111 #
#4000
1!
b1 $
1"
b1100100000 #
#4005
0"
b1100100001 #
#4010
b10 $
0!
1"
b1100100010 #
#4015
0"
b1100100011 #
#4020
b11 $
1"
b1100100100 #
#4025
0"
b1100100101 #
#4030
b100 $
1"
b1100100110 #
#4035
0"
b1100100111 #
#4040
b101 $
1"
b1100101000 #
#4045
0"
b1100101001 #
#4050
b110 $
1"
b1100101010 #
#4055
0"
b1100101011 #
#4060
b111 $
1"
b1100101100 #
#4065
0"
b1100101101 #
#4070
b1000 $
1"
b1100101110 #
#4075
0"
b1100101111 #
#4080
b1001 $
1"
b1100110000 #
#4085
0"
b1100110001 #
#4090
b1010 $
1"
b1100110010 #
#4095
0"
b1100110011 #
#4100
b1011 $
1"
b1100110100 #
#4105
0"
b1100110101 #
#4110
b1100 $
1"
b1100110110 #
#4115
0"
b1100110111 #
#4120
b1101 $
1"
b1100111000 #
#4125
0"
b1100111001 #
#4130
b1110 $
1"
b1100111010 #
#4135
0"
b1100111011 #
#4140
b1111 $
1"
b1100111100 #
#4145
0"
b1100111101 #
#4150
b10000 $
1"
b1100111110 #
#4155
0"
b1100111111 #
#4160
b10001 $
1"
b1101000000 #
#4165
0"
b1101000001 #
#4170
b10010 $
1"
b1101000010 #
#4175
0"
b1101000011 #
#4180
b10011 $
1"
b1101000100 #
#4185
0"
b1101000101 #
