base.v
module microwave(input wire [9:0] keypad,
                 input wire clock, startn, stopn, clearn, door_closed,
                 output wire [6:0] sec_ones_segs, sec_tens_segs, min_segs,
                 output wire mag_on);
  
  wire zero, mag, pgt, load;
  wire [3:0] sec_one, sec_ten, min, D;
  
  assign mag_on = mag;

  MagnetronControl mag_control(
    .start(startn),
    .stop(stopn),
    .clear(clearn),
    .door_closed(door_closed),
    .timer_done(zero),
    .Enabler(mag));
  
  encoder encoder_1(
    .keypad(keypad),
    .clk(clock),
    .enablen(mag),
    .D(D),
    .pgt_1hz(pgt),
    .loadn(load));
  
  timer timer_1(
    .data(D),
    .loadn(load),
    .clock(pgt),
    .clrn(clearn),
    .en(mag),
    .sec_ones(sec_one),
    .sec_tens(sec_ten),
    .mins(min),
    .zero(zero));

  decoder decoder_1(
    .sec_ones(sec_one),
    .sec_tens(sec_ten),
    .min(min),
    .sec_ones_segs(sec_ones_segs),
    .sec_tens_segs(sec_tens_segs),
    .min_segs(min_segs));

endmodule

  //módulos
  
  //timer
module timer(
  input wire[3:0] data,
  input wire loadn, clrn, clock, en,
  output wire [3:0] sec_ones, sec_tens, mins,
  output wire zero);
  
  wire en_st, en_min;
  wire zero_so, zero_st, zero_min;
  
  mod_10_bcd unit_sec(.data(data),
    .loadn(loadn),
    .clrn(clrn),
    .clk(clock),
    .en(en),
    .ones(sec_ones),
    .tc(en_st),
    .zero(zero_so));
  
  mod_6_bcd ten_sec(
    .data(sec_ones),
    .loadn(loadn),
    .clrn(clrn),
    .clk(clock),
    .en(en_st),
    .tens(sec_tens),
    .tc(en_min),
    .zero(zero_st));
  
  mod_10_bcd min(
    .data(sec_tens),
    .loadn(loadn),
    .clrn(clrn),
    .clk(clock),
    .en(en_min),
    .ones(mins),
    .zero(zero_min));
  
  assign zero = zero_so && zero_st && zero_min;
  
endmodule
  
module mod_6_bcd(
  input wire [3:0] data,
  input wire loadn, clrn, clk, en,
  output reg [3:0] tens,
  output wire tc, zero);
  
  
  assign tc = ((tens == 4'b0000) && (en == 1)) ? 1 : 0;
  assign zero = (tens == 4'b0000) ? 1 : 0;
  
  always@(posedge clk, negedge clrn)
    begin
      
      if(!clrn)
        begin
          tens <= 0;
        end
      else
        begin
          if(!en)
            begin
              if(!loadn)
                begin
                  tens <= data;
                end
            end
          else
            begin
              if(tens == 0)
                begin
                  tens <= 5;
                end
              else
                begin
                	tens <= tens - 1;
                end
            end
        end
    end
  
endmodule

module mod_10_bcd(
  input wire [3:0] data,
  input wire loadn, clrn, clk, en,
  output reg [3:0] ones,
  output wire tc, zero);

  assign tc = ((ones == 4'b0000) && (en == 1)) ? 1 : 0;
  assign zero = (ones == 4'b0000) ? 1 : 0;
  
  always@(posedge clk, negedge clrn)
    begin
      
      if(!clrn)
        begin
          ones <= 0;
        end
      else
        begin
          if(!en)
            begin
              if(!loadn)
                begin
                  ones <= data;
                end
            end
          else
            begin
              if(ones == 0)
                begin
                  ones <= 9;
                end
              else
                begin
                	ones <= ones - 1;
                end
            end
        end
    end
  
  
endmodule
  
  
  //encoder

module encoder(
    input [9:0] keypad,
    input clk, enablen,

    output wire [3:0] D,
    output wire pgt_1hz, loadn
);

    wire validn, div_clk, pgt;

    priority_encoder p_encoder (.keypad(keypad), .enablen(enablen), .D(D), .validn(validn));

    freq_div div (.clock(clk), .div_clk(div_clk));

    counter_mod7 counter (.clk(clk), .clear(validn), .pgt(pgt));

    mux mux1 (.sel(enablen), .pgt(pgt), .clk(div_clk), .out(pgt_1hz));

    assign loadn = validn;

endmodule

module freq_div(
    input wire clock,
    output reg div_clk);
  
  integer count = 0;
  
  always @(posedge clock) begin
      if(count != 100)
        begin
          div_clk = 0;
        end

      else
        begin
          count = 0;
          div_clk = 1;
        end
      
      count = count + 1;
  end
endmodule

module mux(
    input wire sel, pgt, clk,
    output reg out
);

    always @(*) begin
        if (sel == 0) begin
            out = clk;
        end

        else begin
            out = pgt;
        end
    end
endmodule


module counter_mod7(
    input clk, clear,

    output reg pgt
);

    integer count = 0;

    always @(negedge clear) begin
        if (count == 7) begin
            count = 0;
        end
    end

    always @(posedge clk) begin
        if (count < 7) begin
            count = count + 1;
        end

        if (count == 4) begin
            pgt = 1;
        end

        else begin
            pgt = 0;
        end
    end
endmodule


module priority_encoder (
    input [9:0] keypad,
    input enablen,

    output reg [3:0] D,
    output reg validn
);

    always @(keypad, enablen) begin
        // O microondas está funcionando, logo não é possível pressionar nenhuma tecla
        if (enablen == 0) begin
            validn = 1;
        end

        else begin
            case (keypad)
                // 1
                10'b1000000000: begin
                    D = 4'b0001;
                    validn = 0;
                end

                // 2
                10'b0100000000: begin
                    D = 4'b0010;
                    validn = 0;
                end
                
                // 3
                10'b0010000000: begin
                    D = 4'b0011;
                    validn = 0;
                end
                
                // 4
                10'b0001000000: begin
                    D = 4'b0100;
                    validn = 0;
                end

                // 5
                10'b0000100000: begin
                    D = 4'b0101;
                    validn = 0;
                end

                // 6
                10'b0000010000: begin
                    D = 4'b0110;
                    validn = 0;
                end

                // 7
                10'b0000001000: begin
                    D = 4'b0111;
                    validn = 0;
                end

                // 8
                10'b1000000100: begin
                    D = 4'b1000;
                    validn = 0;
                end

                // 9
                10'b0000000010: begin
                    D = 4'b1001;
                    validn = 0;
                end

                // 0
                10'b0000000001: begin
                    D = 4'b0000;
                    validn = 0;
                end

                // Caso em que nenhuma tecla está sendo pressionada
                10'b0000000000: validn = 1;

                // Input inválido
                default: begin
                    validn = 1;
                end
            endcase
        end
    end
endmodule
  

//decoder
module decoder(input wire[3:0] sec_ones, sec_tens, min,
               output wire[6:0] sec_ones_segs, sec_tens_segs, min_segs);
  
  assign min_segs = (min == 4'b0000) ? 7'b000_0000 :
    				(min == 4'b0001) ? 7'b011_0000 : 
    				(min == 4'b0010) ? 7'b110_1101 : 
    				(min == 4'b0011) ? 7'b111_1001 : 
                    (min == 4'b0100) ? 7'b011_0011 : 
    				(min == 4'b0101) ? 7'b101_1011 : 
    				(min == 4'b0110) ? 7'b001_1111 : 
    				(min == 4'b0111) ? 7'b111_0000 :
    				(min == 4'b1000) ? 7'b111_1111 :
    				(min == 4'b1001) ? 7'b111_0011 :
    				7'b000_0000;
  
 
  assign sec_tens_segs =  ((min_segs == 7'b000_0000) && (sec_tens == 4'b0000)) ? 7'b000_0000:
    					  (sec_tens == 4'b0000) ? 7'b111_1110 :
                          (sec_tens == 4'b0001) ? 7'b011_0000 :
                          (sec_tens == 4'b0010) ? 7'b110_1101 :
                          (sec_tens == 4'b0011) ? 7'b111_1001 :
                          (sec_tens == 4'b0100) ? 7'b011_0011 : 
                          (sec_tens == 4'b0101) ? 7'b101_1011 : 
                          (sec_tens == 4'b0110) ? 7'b001_1111 : 
                          (sec_tens == 4'b0111) ? 7'b111_0000 : 
                          (sec_tens == 4'b1000) ? 7'b111_1111 : 
                          (sec_tens == 4'b1001) ? 7'b111_0011 : 
                          7'b000_0000;
 
  assign sec_ones_segs = ((min_segs == 7'b000_0000) && (sec_tens_segs == 7'b000_0000) && (sec_ones == 4'b0000)) ? 7'b000_0000:
     					 (sec_ones == 4'b0000) ? 7'b111_1110 :
                         (sec_ones == 4'b0001) ? 7'b011_0000 :
                         (sec_ones == 4'b0010) ? 7'b110_1101 :
                         (sec_ones == 4'b0011) ? 7'b111_1001 :
                         (sec_ones == 4'b0100) ? 7'b011_0011 :
                         (sec_ones == 4'b0101) ? 7'b101_1011 :
                         (sec_ones == 4'b0110) ? 7'b001_1111 :
                         (sec_ones == 4'b0111) ? 7'b111_0000 :
                         (sec_ones == 4'b1000) ? 7'b111_1111 :
                         (sec_ones == 4'b1001) ? 7'b111_0011 :
                         7'b000_0000;
  
endmodule
  
  
//mag-control
  
module MagnetronControl(
  input start,
  input stop,
  input clear,
  input door_closed,
  input timer_done,
  output Enabler);
  

  wire set, reset;
  
  logic_and_or_not B_logic(start, stop, clear, door_closed, timer_done, set, reset);
  sr_latch latch(set, reset, Enabler);
 
  
endmodule


module logic_and_or_not(input start, input stop, input clear, input door_closed, input timer_done, output wire set, output wire reset);
	
  	assign set = (start && door_closed);
  	assign reset = (stop || clear || ~door_closed || timer_done); 
  
endmodule


module sr_latch(
    input set,
    input reset,
    output Q
    );
	
  	reg Q;
  
    always @(*)
      begin
        Q = (~set && reset) ? 0:
          (set && ~reset) ? 1:
          (set && reset) ? 0:
          Q;
      end
endmodule

encoder/priority_encoder/priority_encoder_tb.v
`timescale 1ms/1ms

module priority_encoder_tb;
    reg [9:0] keypad_tb;
    reg enablen_tb;

    wire [3:0] D_tb;
    wire validn_tb;

    priority_encoder uut (
    .keypad(keypad_tb),
    .enablen(enablen_tb),
    .D(D_tb),
    .validn(validn_tb));

    initial
        begin

            $dumpfile("priority_encoder.vcd");
            $dumpvars(0, priority_encoder_tb);

            enablen_tb = 1;
            #5;
        
            keypad_tb = 10'b0000000000;
            #5;

            keypad_tb = 10'b1000000000;
            #100;

            keypad_tb = 10'b0000000000;
            #5;

            keypad_tb = 10'b0000000001;
            #100;

            keypad_tb = 10'b0000000000;
            #5;

            keypad_tb = 10'b0000001000;
            #100;

            keypad_tb = 10'b0000000000;
            #5;

            keypad_tb = 10'b1000000000;
            #100;

            keypad_tb = 10'b0000000000;
            #5;

            // Input inválido
            keypad_tb = 10'b1000010000;
            #100;

            $finish;
        end
endmodule

Encoder/Priority_encoder/priority_encoder.vcd
$date
	Wed May 11 19:04:21 2022
$end
$version
	Icarus Verilog
$end
$timescale
	1ms
$end
$scope module priority_encoder_tb $end
$var wire 1 ! validn_tb $end
$var wire 4 " D_tb [3:0] $end
$var reg 1 # enablen_tb $end
$var reg 10 $ keypad_tb [9:0] $end
$scope module uut $end
$var wire 1 # enablen $end
$var wire 10 % keypad [9:0] $end
$var reg 4 & D [3:0] $end
$var reg 1 ! validn $end
$upscope $end
$upscope $end
$enddefinitions $end
#0
$dumpvars
bx &
bx %
bx $
1#
bx "
1!
$end
#5
1!
b0 $
b0 %
#10
b1 "
b1 &
0!
b1000000000 $
b1000000000 %
#110
1!
b0 $
b0 %
#115
b0 "
b0 &
0!
b1 $
b1 %
#215
1!
b0 $
b0 %
#220
b111 "
b111 &
0!
b1000 $
b1000 %
#320
1!
b0 $
b0 %
#325
b1 "
b1 &
0!
b1000000000 $
b1000000000 %
#425
1!
b0 $
b0 %
#430
1!
b1000010000 $
b1000010000 %
