Encoder/Counter/nrc_mod7.v
module counter_mod7(
    input clk, clear,

    output reg pgt
);

    integer count = 0;

    always @(posedge clear) begin
        if (count == 7) begin
            count = 0;
        end
    end

    always @(posedge clk) begin
        if (count < 7) begin
            count = count + 1;
        end

        if (count == 4) begin
            pgt = 1;
        end

        else begin
            pgt = 0;
        end
    end
endmodule

Encoder/Counter/counter_tb.v
module counter_mod7_tb;
  reg clk, clear;
  wire pgt;
  
  counter_mod7 uut(
    .clk(clk),
    .clear(clear),
    .pgt(pgt));
  
  initial begin
    $dumpfile("counter_mod7.vcd");
    $dumpvars(0,counter_mod7_tb);
  end
  
  initial begin
    clk = 0;
    forever #500 clk = ~clk;
  end
  
  initial begin
    clear = 1;
    #50000;
    
    clear = 0;
    #5000;
    clear = 1;
    #5000;
    
    clear = 0;
    #1000;
    clear = 1;
    $finish();
  end
endmodule

Encoder/Counter/counter_mod7.vcd
$date
	Thu May 12 22:11:34 2022
$end
$version
	Icarus Verilog
$end
$timescale
	1s
$end
$scope module counter_mod7_tb $end
$var wire 1 ! pgt $end
$var reg 1 " clear $end
$var reg 1 # clk $end
$scope module uut $end
$var wire 1 " clear $end
$var wire 1 # clk $end
$var reg 1 ! pgt $end
$var integer 32 $ count [31:0] $end
$upscope $end
$upscope $end
$enddefinitions $end
#0
$dumpvars
b0 $
0#
1"
x!
$end
#500
0!
b1 $
1#
#1000
0#
#1500
b10 $
1#
#2000
0#
#2500
b11 $
1#
#3000
0#
#3500
1!
b100 $
1#
#4000
0#
#4500
0!
b101 $
1#
#5000
0#
#5500
b110 $
1#
#6000
0#
#6500
b111 $
1#
