Timer/Timer/timer_EDA.v
module timer(
  input wire[3:0] data,
  input wire loadn, clrn, clock, en,
  output wire [3:0] sec_ones, sec_tens, mins,
  output wire zero);
  
  wire en_st, en_min;
  wire zero_so, zero_st, zero_min;
  
  mod_10_bcd unit_sec(
    .data(data),
    .loadn(loadn),
    .clrn(clrn),
    .clk(clock),
    .en(en),
    .ones(sec_ones),
    .tc(en_st),
    .zero(zero_so));
  
  mod_6_bcd ten_sec(
    .data(sec_ones),
    .loadn(loadn),
    .clrn(clrn),
    .clk(clock),
    .en(en_st),
    .tens(sec_tens),
    .tc(en_min),
    .zero(zero_st));
  
  mod_10_bcd min(
    .data(sec_tens),
    .loadn(loadn),
    .clrn(clrn),
    .clk(clock),
    .en(en_min),
    .ones(mins),
    .zero(zero_min));
  
  assign zero = zero_so && zero_st && zero_min;
  
endmodule


module mod_6_bcd(
  input wire [3:0] data,
  input wire loadn, clrn, clk, en,
  output reg [3:0] tens,
  output wire tc, zero);
  
  //active low - loadn (sinc) e clrn(assinc)
  //active high - en -> quando en = 1 permite que a contagem seja feita
  //tc = 1 quando tens = 4'b000 -> reinicia a contagem
  //zero = 1 quando tens = 4'b000
  
  
  assign tc = ((tens == 4'b0000) && (en == 1)) ? 1 : 0;
  assign zero = (tens === 4'b0000 || tens === 4'bXXXX) ? 1 : 0;
  
  initial begin
    tens = 4'b0000;
  end
  
  always@(negedge clrn) begin
    tens <= 0;
  end
  
  always@(posedge clk) begin
          if(!en)
            begin
              if(!loadn)
                  tens <= data;
            end
          else
            begin
              if(tens == 0)
                  tens <= 5;
              else
                tens <= tens - 1;
            end
        end
  
endmodule


module mod_10_bcd(
  input wire [3:0] data,
  input wire loadn, clrn, clk, en,
  output reg [3:0] ones,
  output wire tc, zero);
  
  //active low - loadn (sinc) e clrn(assinc)
  //active high - en -> quando en = 1 permite que a contagem seja feita
  //tc = 1 quando ones = 4'b000 -> reinicia a contagem
  //zero = 1 quando ones = 4'b000

  assign tc = ((ones == 4'b0000) && (en == 1)) ? 1 : 0;
  assign zero = (ones === 4'b0000 || ones === 4'bXXXX) ? 1 : 0;
  
  always@(negedge clrn) begin
    ones <= 0;
  end
  
  always@(posedge clk) begin
          if(!en)
            begin
              if(!loadn)
                  ones <= data;
            end
          else
            begin
              if(ones == 0)
                  ones <= 9;
              else
                ones <= ones - 1;
            end
        end
  
  
endmodule

Timer/Timer/timer_tb.v
module timer_tb;
  reg [3:0] Data;
  reg Clock, Clear, Load, En;
  
  integer i;
  wire [3:0] Sec_ones, Sec_tens, Mins;
  wire Zero;
  
  timer uut(
    .data(Data),
    .loadn(Load),
    .clrn(Clear),
    .clock(Clock),
    .en(En),
    .sec_ones(Sec_ones),
    .sec_tens(Sec_tens),
    .mins(Mins),
    .zero(Zero));
  
  initial begin
    $dumpfile("timer_tb.vcd");
    $dumpvars(0,timer_tb);
  end
  
  initial begin
    
    for(i = 0; i < 2500; i = i+1) begin
          #500 Clock <= !Clock;
        end
  end
  
  initial begin
    Load = 0; Clear = 0; En = 0; Data = 4'b0111; Clock = 1; //insere o 7 nas unidades de segundos
    #1000;
    Data = 4'b0010; //insere o 2 nas unidades de segundos e passa o 7 para dezena de segundos 
    
    #1000;
    
    Data = 4'b0100; //insere o 4 nas unidades de segundos, passa o 2 para dezena de segundos e o 7 para minutos
    
    #1000;
    Load = 1;
    En = 1;
    
    #5000;
    En = 0; //pausa
    
    #5000;
    
    Clear = 0; //limpa
    
    #5000
    
    Clear = 1;
    
    En = 1; //reinicia contagem
    
    #15000;
    
    En = 0; //pausa o cronometro
  end
endmodule

Timer/Timer/timer_tb.vcd
$date
	Thu May 12 22:16:51 2022
$end
$version
	Icarus Verilog
$end
$timescale
	1s
$end
$scope module timer_tb $end
$var wire 1 ! Zero $end
$var wire 4 " Sec_tens [3:0] $end
$var wire 4 # Sec_ones [3:0] $end
$var wire 4 $ Mins [3:0] $end
$var reg 1 % Clear $end
$var reg 1 & Clock $end
$var reg 4 ' Data [3:0] $end
$var reg 1 ( En $end
$var reg 1 ) Load $end
$var integer 32 * i [31:0] $end
$scope module uut $end
$var wire 1 & clock $end
$var wire 1 % clrn $end
$var wire 4 + data [3:0] $end
$var wire 1 ( en $end
$var wire 1 ) loadn $end
$var wire 1 ! zero $end
$var wire 1 , zero_st $end
$var wire 1 - zero_so $end
$var wire 1 . zero_min $end
$var wire 4 / sec_tens [3:0] $end
$var wire 4 0 sec_ones [3:0] $end
$var wire 4 1 mins [3:0] $end
$var wire 1 2 en_st $end
$var wire 1 3 en_min $end
$scope module min $end
$var wire 1 & clk $end
$var wire 1 % clrn $end
$var wire 1 ) loadn $end
$var wire 1 . zero $end
$var wire 1 4 tc $end
$var wire 1 3 en $end
$var wire 4 5 data [3:0] $end
$var reg 4 6 ones [3:0] $end
$upscope $end
$scope module ten_sec $end
$var wire 1 & clk $end
$var wire 1 % clrn $end
$var wire 1 ) loadn $end
$var wire 1 , zero $end
$var wire 1 3 tc $end
$var wire 1 2 en $end
$var wire 4 7 data [3:0] $end
$var reg 4 8 tens [3:0] $end
$upscope $end
$scope module unit_sec $end
$var wire 1 & clk $end
$var wire 1 % clrn $end
$var wire 4 9 data [3:0] $end
$var wire 1 ( en $end
$var wire 1 ) loadn $end
$var wire 1 - zero $end
$var wire 1 2 tc $end
$var reg 4 : ones [3:0] $end
$upscope $end
$upscope $end
$upscope $end
$enddefinitions $end
#0
$dumpvars
b111 :
b111 9
bx 8
b111 7
bx 6
bx 5
04
03
02
bx 1
b111 0
bx /
0.
0-
0,
b111 +
b0 *
0)
0(
b111 '
1&
0%
bx $
b111 #
bx "
0!
$end
#500
0&
b1 *
#1000
b111 "
b111 /
b111 5
b111 8
b10 #
b10 0
b10 7
b10 :
1&
b10 *
b10 '
b10 +
b10 9
#1500
0&
b11 *
#2000
b100 #
b100 0
b100 7
b100 :
b10 "
b10 /
b10 5
b10 8
b111 $
b111 1
b111 6
1&
b100 *
b100 '
b100 +
b100 9
#2500
0&
b101 *
#3000
b11 #
b11 0
b11 7
b11 :
1&
b110 *
1(
1)
#3500
0&
b111 *
#4000
b10 #
b10 0
b10 7
b10 :
1&
b1000 *
#4500
0&
b1001 *
#5000
b1 #
b1 0
b1 7
b1 :
1&
b1010 *
#5500
0&
b1011 *
#6000
12
1-
b0 #
b0 0
b0 7
b0 :
1&
b1100 *
#6500
0&
b1101 *
#7000
02
0-
b1 "
b1 /
b1 5
b1 8
b1001 #
b1001 0
b1001 7
b1001 :
1&
b1110 *
#7500
0&
b1111 *
#8000
1&
b10000 *
0(
#8500
0&
b10001 *
#9000
1&
b10010 *
#9500
0&
b10011 *
#10000
1&
b10100 *
#10500
0&
b10101 *
#11000
1&
b10110 *
#11500
0&
b10111 *
#12000
1&
b11000 *
#12500
0&
b11001 *
#13000
1&
b11010 *
#13500
0&
b11011 *
#14000
1&
b11100 *
#14500
0&
b11101 *
#15000
1&
b11110 *
#15500
0&
b11111 *
#16000
1&
b100000 *
#16500
0&
b100001 *
#17000
1&
b100010 *
#17500
0&
b100011 *
#18000
b1000 #
b1000 0
b1000 7
b1000 :
1&
b100100 *
1(
1%
#18500
0&
b100101 *
#19000
b111 #
b111 0
b111 7
b111 :
1&
b100110 *
#19500
0&
b100111 *
#20000
b110 #
b110 0
b110 7
b110 :
1&
b101000 *
#20500
0&
b101001 *
#21000
b101 #
b101 0
b101 7
b101 :
1&
b101010 *
#21500
0&
b101011 *
#22000
b100 #
b100 0
b100 7
b100 :
1&
b101100 *
#22500
0&
b101101 *
#23000
b11 #
b11 0
b11 7
b11 :
1&
b101110 *
#23500
0&
b101111 *
#24000
b10 #
b10 0
b10 7
b10 :
1&
b110000 *
#24500
0&
b110001 *
#25000
b1 #
b1 0
b1 7
b1 :
1&
b110010 *
#25500
0&
b110011 *
#26000
12
1-
b0 #
b0 0
b0 7
b0 :
1&
b110100 *
#26500
0&
b110101 *
#27000
03
02
1,
0-
b0 "
b0 /
b0 5
b0 8
b1001 #
b1001 0
b1001 7
b1001 :
1&
b110110 *
#27500
0&
b110111 *
#28000
b1000 #
b1000 0
b1000 7
b1000 :
1&
b111000 *
#28500
0&
b111001 *
#29000
b111 #
b111 0
b111 7
b111 :
1&
b111010 *
#29500
0&
b111011 *
#30000
b110 #
b110 0
b110 7
b110 :
1&
b111100 *
#30500
0&
b111101 *
#31000
b101 #
b101 0
b101 7
b101 :
1&
b111110 *
#31500
0&
b111111 *
#32000
b100 #
b100 0
b100 7
b100 :
1&
b1000000 *
#32500
0&
b1000001 *
#33000
1&
b1000010 *
0(
#33500
0&
b1000011 *
#34000
1&
b1000100 *
#34500
0&
b1000101 *
#35000
1&
b1000110 *
#35500
0&
b1000111 *
#36000
1&
b1001000 *
#36500
0&
b1001001 *
#37000
1&
b1001010 *
#37500
0&
b1001011 *
#38000
1&
b1001100 *
#38500
0&
b1001101 *
#39000
1&
b1001110 *
#39500
0&
b1001111 *
#40000
1&
b1010000 *
#40500
0&
b1010001 *
#41000
1&
b1010010 *
#41500
0&
b1010011 *
#42000
1&
b1010100 *
#42500
0&
b1010101 *
#43000
1&
b1010110 *
#43500
0&
b1010111 *
#44000
1&
b1011000 *
#44500
0&
b1011001 *
#45000
1&
b1011010 *
#45500
0&
b1011011 *
#46000
1&
b1011100 *
#46500
0&
b1011101 *
#47000
1&
b1011110 *
#47500
0&
b1011111 *
#48000
1&
b1100000 *
#48500
0&
b1100001 *
#49000
1&
b1100010 *
#49500
0&
b1100011 *
#50000
1&
b1100100 *
#50500
0&
b1100101 *
#51000
1&
b1100110 *
#51500
0&
b1100111 *
#52000
1&
b1101000 *
#52500
0&
b1101001 *
#53000
1&
b1101010 *
#53500
0&
b1101011 *
#54000
1&
b1101100 *
#54500
0&
b1101101 *
#55000
1&
b1101110 *
#55500
0&
b1101111 *
#56000
1&
b1110000 *
#56500
0&
b1110001 *
#57000
1&
b1110010 *
#57500
0&
b1110011 *
#58000
1&
b1110100 *
#58500
0&
b1110101 *
#59000
1&
b1110110 *
#59500
0&
b1110111 *
#60000
1&
b1111000 *
#60500
0&
b1111001 *
#61000
1&
b1111010 *
#61500
0&
b1111011 *
#62000
1&
b1111100 *
#62500
0&
b1111101 *
#63000
1&
b1111110 *
#63500
0&
b1111111 *
#64000
1&
b10000000 *
#64500
0&
b10000001 *
#65000
1&
b10000010 *
#65500
0&
b10000011 *
#66000
1&
b10000100 *
#66500
0&
b10000101 *
#67000
1&
b10000110 *
#67500
0&
b10000111 *
#68000
1&
b10001000 *
#68500
0&
b10001001 *
#69000
1&
b10001010 *
#69500
0&
b10001011 *
#70000
1&
b10001100 *
#70500
0&
b10001101 *
#71000
1&
b10001110 *
#71500
0&
b10001111 *
#72000
1&
b10010000 *
#72500
0&
b10010001 *
#73000
1&
b10010010 *
#73500
0&
b10010011 *
#74000
1&
b10010100 *
#74500
0&
b10010101 *
#75000
1&
b10010110 *
#75500
0&
b10010111 *
#76000
1&
b10011000 *
#76500
0&
b10011001 *
#77000
1&
b10011010 *
#77500
0&
b10011011 *
#78000
1&
b10011100 *
#78500
0&
b10011101 *
#79000
1&
b10011110 *
#79500
0&
b10011111 *
#80000
1&
b10100000 *
#80500
0&
b10100001 *
#81000
1&
b10100010 *
#81500
0&
b10100011 *
#82000
1&
b10100100 *
#82500
0&
b10100101 *
#83000
1&
b10100110 *
#83500
0&
b10100111 *
#84000
1&
b10101000 *
#84500
0&
b10101001 *
#85000
1&
b10101010 *
#85500
0&
b10101011 *
#86000
1&
b10101100 *
#86500
0&
b10101101 *
#87000
1&
b10101110 *
#87500
0&
b10101111 *
#88000
1&
b10110000 *
#88500
0&
b10110001 *
#89000
1&
b10110010 *
#89500
0&
b10110011 *
#90000
1&
b10110100 *
#90500
0&
b10110101 *
#91000
1&
b10110110 *
#91500
0&
b10110111 *
#92000
1&
b10111000 *
#92500
0&
b10111001 *
#93000
1&
b10111010 *
#93500
0&
b10111011 *
#94000
1&
b10111100 *
#94500
0&
b10111101 *
#95000
1&
b10111110 *
#95500
0&
b10111111 *
#96000
1&
b11000000 *
#96500
0&
b11000001 *
#97000
1&
b11000010 *
#97500
0&
b11000011 *
#98000
1&
b11000100 *
#98500
0&
b11000101 *
#99000
1&
b11000110 *
#99500
0&
b11000111 *
#100000
1&
b11001000 *
#100500
0&
b11001001 *
#101000
1&
b11001010 *
#101500
0&
b11001011 *
#102000
1&
b11001100 *
#102500
0&
b11001101 *
#103000
1&
b11001110 *
#103500
0&
b11001111 *
#104000
1&
b11010000 *
#104500
0&
b11010001 *
#105000
1&
b11010010 *
#105500
0&
b11010011 *
#106000
1&
b11010100 *
#106500
0&
b11010101 *
#107000
1&
b11010110 *
#107500
0&
b11010111 *
#108000
1&
b11011000 *
#108500
0&
b11011001 *
#109000
1&
b11011010 *
#109500
0&
b11011011 *
#110000
1&
b11011100 *
#110500
0&
b11011101 *
#111000
1&
b11011110 *
#111500
0&
b11011111 *
#112000
1&
b11100000 *
#112500
0&
b11100001 *
#113000
1&
b11100010 *
#113500
0&
b11100011 *
#114000
1&
b11100100 *
#114500
0&
b11100101 *
#115000
1&
b11100110 *
#115500
0&
b11100111 *
#116000
1&
b11101000 *
#116500
0&
b11101001 *
#117000
1&
b11101010 *
#117500
0&
b11101011 *
#118000
1&
b11101100 *
#118500
0&
b11101101 *
#119000
1&
b11101110 *
#119500
0&
b11101111 *
#120000
1&
b11110000 *
#120500
0&
b11110001 *
#121000
1&
b11110010 *
#121500
0&
b11110011 *
#122000
1&
b11110100 *
#122500
0&
b11110101 *
#123000
1&
b11110110 *
#123500
0&
b11110111 *
#124000
1&
b11111000 *
#124500
0&
b11111001 *
#125000
1&
b11111010 *
#125500
0&
b11111011 *
#126000
1&
b11111100 *
#126500
0&
b11111101 *
#127000
1&
b11111110 *
#127500
0&
b11111111 *
#128000
1&
b100000000 *
#128500
0&
b100000001 *
#129000
1&
b100000010 *
#129500
0&
b100000011 *
#130000
1&
b100000100 *
#130500
0&
b100000101 *
#131000
1&
b100000110 *
#131500
0&
b100000111 *
#132000
1&
b100001000 *
#132500
0&
b100001001 *
#133000
1&
b100001010 *
#133500
0&
b100001011 *
#134000
1&
b100001100 *
#134500
0&
b100001101 *
#135000
1&
b100001110 *
#135500
0&
b100001111 *
#136000
1&
b100010000 *
#136500
0&
b100010001 *
#137000
1&
b100010010 *
#137500
0&
b100010011 *
#138000
1&
b100010100 *
#138500
0&
b100010101 *
#139000
1&
b100010110 *
#139500
0&
b100010111 *
#140000
1&
b100011000 *
#140500
0&
b100011001 *
#141000
1&
b100011010 *
#141500
0&
b100011011 *
#142000
1&
b100011100 *
#142500
0&
b100011101 *
#143000
1&
b100011110 *
#143500
0&
b100011111 *
#144000
1&
b100100000 *
#144500
0&
b100100001 *
#145000
1&
b100100010 *
#145500
0&
b100100011 *
#146000
1&
b100100100 *
#146500
0&
b100100101 *
#147000
1&
b100100110 *
#147500
0&
b100100111 *
#148000
1&
b100101000 *
#148500
0&
b100101001 *
#149000
1&
b100101010 *
#149500
0&
b100101011 *
#150000
1&
b100101100 *
#150500
0&
b100101101 *
#151000
1&
b100101110 *
#151500
0&
b100101111 *
#152000
1&
b100110000 *
#152500
0&
b100110001 *
#153000
1&
b100110010 *
#153500
0&
b100110011 *
#154000
1&
b100110100 *
#154500
0&
b100110101 *
#155000
1&
b100110110 *
#155500
0&
b100110111 *
#156000
1&
b100111000 *
#156500
0&
b100111001 *
#157000
1&
b100111010 *
#157500
0&
b100111011 *
#158000
1&
b100111100 *
#158500
0&
b100111101 *
#159000
1&
b100111110 *
#159500
0&
b100111111 *
#160000
1&
b101000000 *
#160500
0&
b101000001 *
#161000
1&
b101000010 *
#161500
0&
b101000011 *
#162000
1&
b101000100 *
#162500
0&
b101000101 *
#163000
1&
b101000110 *
#163500
0&
b101000111 *
#164000
1&
b101001000 *
#164500
0&
b101001001 *
#165000
1&
b101001010 *
#165500
0&
b101001011 *
#166000
1&
b101001100 *
#166500
0&
b101001101 *
#167000
1&
b101001110 *
#167500
0&
b101001111 *
#168000
1&
b101010000 *
#168500
0&
b101010001 *
#169000
1&
b101010010 *
#169500
0&
b101010011 *
#170000
1&
b101010100 *
#170500
0&
b101010101 *
#171000
1&
b101010110 *
#171500
0&
b101010111 *
#172000
1&
b101011000 *
#172500
0&
b101011001 *
#173000
1&
b101011010 *
#173500
0&
b101011011 *
#174000
1&
b101011100 *
#174500
0&
b101011101 *
#175000
1&
b101011110 *
#175500
0&
b101011111 *
#176000
1&
b101100000 *
#176500
0&
b101100001 *
#177000
1&
b101100010 *
#177500
0&
b101100011 *
#178000
1&
b101100100 *
#178500
0&
b101100101 *
#179000
1&
b101100110 *
#179500
0&
b101100111 *
#180000
1&
b101101000 *
#180500
0&
b101101001 *
#181000
1&
b101101010 *
#181500
0&
b101101011 *
#182000
1&
b101101100 *
#182500
0&
b101101101 *
#183000
1&
b101101110 *
#183500
0&
b101101111 *
#184000
1&
b101110000 *
#184500
0&
b101110001 *
#185000
1&
b101110010 *
#185500
0&
b101110011 *
#186000
1&
b101110100 *
#186500
0&
b101110101 *
#187000
1&
b101110110 *
#187500
0&
b101110111 *
#188000
1&
b101111000 *
#188500
0&
b101111001 *
#189000
1&
b101111010 *
#189500
0&
b101111011 *
#190000
1&
b101111100 *
#190500
0&
b101111101 *
#191000
1&
b101111110 *
#191500
0&
b101111111 *
#192000
1&
b110000000 *
#192500
0&
b110000001 *
#193000
1&
b110000010 *
#193500
0&
b110000011 *
#194000
1&
b110000100 *
#194500
0&
b110000101 *
#195000
1&
b110000110 *
#195500
0&
b110000111 *
#196000
1&
b110001000 *
#196500
0&
b110001001 *
#197000
1&
b110001010 *
#197500
0&
b110001011 *
#198000
1&
b110001100 *
#198500
0&
b110001101 *
#199000
1&
b110001110 *
#199500
0&
b110001111 *
#200000
1&
b110010000 *
#200500
0&
b110010001 *
#201000
1&
b110010010 *
#201500
0&
b110010011 *
#202000
1&
b110010100 *
#202500
0&
b110010101 *
#203000
1&
b110010110 *
#203500
0&
b110010111 *
#204000
1&
b110011000 *
#204500
0&
b110011001 *
#205000
1&
b110011010 *
#205500
0&
b110011011 *
#206000
1&
b110011100 *
#206500
0&
b110011101 *
#207000
1&
b110011110 *
#207500
0&
b110011111 *
#208000
1&
b110100000 *
#208500
0&
b110100001 *
#209000
1&
b110100010 *
#209500
0&
b110100011 *
#210000
1&
b110100100 *
#210500
0&
b110100101 *
#211000
1&
b110100110 *
#211500
0&
b110100111 *
#212000
1&
b110101000 *
#212500
0&
b110101001 *
#213000
1&
b110101010 *
#213500
0&
b110101011 *
#214000
1&
b110101100 *
#214500
0&
b110101101 *
#215000
1&
b110101110 *
#215500
0&
b110101111 *
#216000
1&
b110110000 *
#216500
0&
b110110001 *
#217000
1&
b110110010 *
#217500
0&
b110110011 *
#218000
1&
b110110100 *
#218500
0&
b110110101 *
#219000
1&
b110110110 *
#219500
0&
b110110111 *
#220000
1&
b110111000 *
#220500
0&
b110111001 *
#221000
1&
b110111010 *
#221500
0&
b110111011 *
#222000
1&
b110111100 *
#222500
0&
b110111101 *
#223000
1&
b110111110 *
#223500
0&
b110111111 *
#224000
1&
b111000000 *
#224500
0&
b111000001 *
#225000
1&
b111000010 *
#225500
0&
b111000011 *
#226000
1&
b111000100 *
#226500
0&
b111000101 *
#227000
1&
b111000110 *
#227500
0&
b111000111 *
#228000
1&
b111001000 *
#228500
0&
b111001001 *
#229000
1&
b111001010 *
#229500
0&
b111001011 *
#230000
1&
b111001100 *
#230500
0&
b111001101 *
#231000
1&
b111001110 *
#231500
0&
b111001111 *
#232000
1&
b111010000 *
#232500
0&
b111010001 *
#233000
1&
b111010010 *
#233500
0&
b111010011 *
#234000
1&
b111010100 *
#234500
0&
b111010101 *
#235000
1&
b111010110 *
#235500
0&
b111010111 *
#236000
1&
b111011000 *
#236500
0&
b111011001 *
#237000
1&
b111011010 *
#237500
0&
b111011011 *
#238000
1&
b111011100 *
#238500
0&
b111011101 *
#239000
1&
b111011110 *
#239500
0&
b111011111 *
#240000
1&
b111100000 *
#240500
0&
b111100001 *
#241000
1&
b111100010 *
#241500
0&
b111100011 *
#242000
1&
b111100100 *
#242500
0&
b111100101 *
#243000
1&
b111100110 *
#243500
0&
b111100111 *
#244000
1&
b111101000 *
#244500
0&
b111101001 *
#245000
1&
b111101010 *
#245500
0&
b111101011 *
#246000
1&
b111101100 *
#246500
0&
b111101101 *
#247000
1&
b111101110 *
#247500
0&
b111101111 *
#248000
1&
b111110000 *
#248500
0&
b111110001 *
#249000
1&
b111110010 *
#249500
0&
b111110011 *
#250000
1&
b111110100 *
#250500
0&
b111110101 *
#251000
1&
b111110110 *
#251500
0&
b111110111 *
#252000
1&
b111111000 *
#252500
0&
b111111001 *
#253000
1&
b111111010 *
#253500
0&
b111111011 *
#254000
1&
b111111100 *
#254500
0&
b111111101 *
#255000
1&
b111111110 *
#255500
0&
b111111111 *
#256000
1&
b1000000000 *
#256500
0&
b1000000001 *
#257000
1&
b1000000010 *
#257500
0&
b1000000011 *
#258000
1&
b1000000100 *
#258500
0&
b1000000101 *
#259000
1&
b1000000110 *
#259500
0&
b1000000111 *
#260000
1&
b1000001000 *
#260500
0&
b1000001001 *
#261000
1&
b1000001010 *
#261500
0&
b1000001011 *
#262000
1&
b1000001100 *
#262500
0&
b1000001101 *
#263000
1&
b1000001110 *
#263500
0&
b1000001111 *
#264000
1&
b1000010000 *
#264500
0&
b1000010001 *
#265000
1&
b1000010010 *
#265500
0&
b1000010011 *
#266000
1&
b1000010100 *
#266500
0&
b1000010101 *
#267000
1&
b1000010110 *
#267500
0&
b1000010111 *
#268000
1&
b1000011000 *
#268500
0&
b1000011001 *
#269000
1&
b1000011010 *
#269500
0&
b1000011011 *
#270000
1&
b1000011100 *
#270500
0&
b1000011101 *
#271000
1&
b1000011110 *
#271500
0&
b1000011111 *
#272000
1&
b1000100000 *
#272500
0&
b1000100001 *
#273000
1&
b1000100010 *
#273500
0&
b1000100011 *
#274000
1&
b1000100100 *
#274500
0&
b1000100101 *
#275000
1&
b1000100110 *
#275500
0&
b1000100111 *
#276000
1&
b1000101000 *
#276500
0&
b1000101001 *
#277000
1&
b1000101010 *
#277500
0&
b1000101011 *
#278000
1&
b1000101100 *
#278500
0&
b1000101101 *
#279000
1&
b1000101110 *
#279500
0&
b1000101111 *
#280000
1&
b1000110000 *
#280500
0&
b1000110001 *
#281000
1&
b1000110010 *
#281500
0&
b1000110011 *
#282000
1&
b1000110100 *
#282500
0&
b1000110101 *
#283000
1&
b1000110110 *
#283500
0&
b1000110111 *
#284000
1&
b1000111000 *
#284500
0&
b1000111001 *
#285000
1&
b1000111010 *
#285500
0&
b1000111011 *
#286000
1&
b1000111100 *
#286500
0&
b1000111101 *
#287000
1&
b1000111110 *
#287500
0&
b1000111111 *
#288000
1&
b1001000000 *
#288500
0&
b1001000001 *
#289000
1&
b1001000010 *
#289500
0&
b1001000011 *
#290000
1&
b1001000100 *
#290500
0&
b1001000101 *
#291000
1&
b1001000110 *
#291500
0&
b1001000111 *
#292000
1&
b1001001000 *
#292500
0&
b1001001001 *
#293000
1&
b1001001010 *
#293500
0&
b1001001011 *
#294000
1&
b1001001100 *
#294500
0&
b1001001101 *
#295000
1&
b1001001110 *
#295500
0&
b1001001111 *
#296000
1&
b1001010000 *
#296500
0&
b1001010001 *
#297000
1&
b1001010010 *
#297500
0&
b1001010011 *
#298000
1&
b1001010100 *
#298500
0&
b1001010101 *
#299000
1&
b1001010110 *
#299500
0&
b1001010111 *
#300000
1&
b1001011000 *
#300500
0&
b1001011001 *
#301000
1&
b1001011010 *
#301500
0&
b1001011011 *
#302000
1&
b1001011100 *
#302500
0&
b1001011101 *
#303000
1&
b1001011110 *
#303500
0&
b1001011111 *
#304000
1&
b1001100000 *
#304500
0&
b1001100001 *
#305000
1&
b1001100010 *
#305500
0&
b1001100011 *
#306000
1&
b1001100100 *
#306500
0&
b1001100101 *
#307000
1&
b1001100110 *
#307500
0&
b1001100111 *
#308000
1&
b1001101000 *
#308500
0&
b1001101001 *
#309000
1&
b1001101010 *
#309500
0&
b1001101011 *
#310000
1&
b1001101100 *
#310500
0&
b1001101101 *
#311000
1&
b1001101110 *
#311500
0&
b1001101111 *
#312000
1&
b1001110000 *
#312500
0&
b1001110001 *
#313000
1&
b1001110010 *
#313500
0&
b1001110011 *
#314000
1&
b1001110100 *
#314500
0&
b1001110101 *
#315000
1&
b1001110110 *
#315500
0&
b1001110111 *
#316000
1&
b1001111000 *
#316500
0&
b1001111001 *
#317000
1&
b1001111010 *
#317500
0&
b1001111011 *
#318000
1&
b1001111100 *
#318500
0&
b1001111101 *
#319000
1&
b1001111110 *
#319500
0&
b1001111111 *
#320000
1&
b1010000000 *
#320500
0&
b1010000001 *
#321000
1&
b1010000010 *
#321500
0&
b1010000011 *
#322000
1&
b1010000100 *
#322500
0&
b1010000101 *
#323000
1&
b1010000110 *
#323500
0&
b1010000111 *
#324000
1&
b1010001000 *
#324500
0&
b1010001001 *
#325000
1&
b1010001010 *
#325500
0&
b1010001011 *
#326000
1&
b1010001100 *
#326500
0&
b1010001101 *
#327000
1&
b1010001110 *
#327500
0&
b1010001111 *
#328000
1&
b1010010000 *
#328500
0&
b1010010001 *
#329000
1&
b1010010010 *
#329500
0&
b1010010011 *
#330000
1&
b1010010100 *
#330500
0&
b1010010101 *
#331000
1&
b1010010110 *
#331500
0&
b1010010111 *
#332000
1&
b1010011000 *
#332500
0&
b1010011001 *
#333000
1&
b1010011010 *
#333500
0&
b1010011011 *
#334000
1&
b1010011100 *
#334500
0&
b1010011101 *
#335000
1&
b1010011110 *
#335500
0&
b1010011111 *
#336000
1&
b1010100000 *
#336500
0&
b1010100001 *
#337000
1&
b1010100010 *
#337500
0&
b1010100011 *
#338000
1&
b1010100100 *
#338500
0&
b1010100101 *
#339000
1&
b1010100110 *
#339500
0&
b1010100111 *
#340000
1&
b1010101000 *
#340500
0&
b1010101001 *
#341000
1&
b1010101010 *
#341500
0&
b1010101011 *
#342000
1&
b1010101100 *
#342500
0&
b1010101101 *
#343000
1&
b1010101110 *
#343500
0&
b1010101111 *
#344000
1&
b1010110000 *
#344500
0&
b1010110001 *
#345000
1&
b1010110010 *
#345500
0&
b1010110011 *
#346000
1&
b1010110100 *
#346500
0&
b1010110101 *
#347000
1&
b1010110110 *
#347500
0&
b1010110111 *
#348000
1&
b1010111000 *
#348500
0&
b1010111001 *
#349000
1&
b1010111010 *
#349500
0&
b1010111011 *
#350000
1&
b1010111100 *
#350500
0&
b1010111101 *
#351000
1&
b1010111110 *
#351500
0&
b1010111111 *
#352000
1&
b1011000000 *
#352500
0&
b1011000001 *
#353000
1&
b1011000010 *
#353500
0&
b1011000011 *
#354000
1&
b1011000100 *
#354500
0&
b1011000101 *
#355000
1&
b1011000110 *
#355500
0&
b1011000111 *
#356000
1&
b1011001000 *
#356500
0&
b1011001001 *
#357000
1&
b1011001010 *
#357500
0&
b1011001011 *
#358000
1&
b1011001100 *
#358500
0&
b1011001101 *
#359000
1&
b1011001110 *
#359500
0&
b1011001111 *
#360000
1&
b1011010000 *
#360500
0&
b1011010001 *
#361000
1&
b1011010010 *
#361500
0&
b1011010011 *
#362000
1&
b1011010100 *
#362500
0&
b1011010101 *
#363000
1&
b1011010110 *
#363500
0&
b1011010111 *
#364000
1&
b1011011000 *
#364500
0&
b1011011001 *
#365000
1&
b1011011010 *
#365500
0&
b1011011011 *
#366000
1&
b1011011100 *
#366500
0&
b1011011101 *
#367000
1&
b1011011110 *
#367500
0&
b1011011111 *
#368000
1&
b1011100000 *
#368500
0&
b1011100001 *
#369000
1&
b1011100010 *
#369500
0&
b1011100011 *
#370000
1&
b1011100100 *
#370500
0&
b1011100101 *
#371000
1&
b1011100110 *
#371500
0&
b1011100111 *
#372000
1&
b1011101000 *
#372500
0&
b1011101001 *
#373000
1&
b1011101010 *
#373500
0&
b1011101011 *
#374000
1&
b1011101100 *
#374500
0&
b1011101101 *
#375000
1&
b1011101110 *
#375500
0&
b1011101111 *
#376000
1&
b1011110000 *
#376500
0&
b1011110001 *
#377000
1&
b1011110010 *
#377500
0&
b1011110011 *
#378000
1&
b1011110100 *
#378500
0&
b1011110101 *
#379000
1&
b1011110110 *
#379500
0&
b1011110111 *
#380000
1&
b1011111000 *
#380500
0&
b1011111001 *
#381000
1&
b1011111010 *
#381500
0&
b1011111011 *
#382000
1&
b1011111100 *
#382500
0&
b1011111101 *
#383000
1&
b1011111110 *
#383500
0&
b1011111111 *
#384000
1&
b1100000000 *
#384500
0&
b1100000001 *
#385000
1&
b1100000010 *
#385500
0&
b1100000011 *
#386000
1&
b1100000100 *
#386500
0&
b1100000101 *
#387000
1&
b1100000110 *
#387500
0&
b1100000111 *
#388000
1&
b1100001000 *
#388500
0&
b1100001001 *
#389000
1&
b1100001010 *
#389500
0&
b1100001011 *
#390000
1&
b1100001100 *
#390500
0&
b1100001101 *
#391000
1&
b1100001110 *
#391500
0&
b1100001111 *
#392000
1&
b1100010000 *
#392500
0&
b1100010001 *
#393000
1&
b1100010010 *
#393500
0&
b1100010011 *
#394000
1&
b1100010100 *
#394500
0&
b1100010101 *
#395000
1&
b1100010110 *
#395500
0&
b1100010111 *
#396000
1&
b1100011000 *
#396500
0&
b1100011001 *
#397000
1&
b1100011010 *
#397500
0&
b1100011011 *
#398000
1&
b1100011100 *
#398500
0&
b1100011101 *
#399000
1&
b1100011110 *
#399500
0&
b1100011111 *
#400000
1&
b1100100000 *
#400500
0&
b1100100001 *
#401000
1&
b1100100010 *
#401500
0&
b1100100011 *
#402000
1&
b1100100100 *
#402500
0&
b1100100101 *
#403000
1&
b1100100110 *
#403500
0&
b1100100111 *
