MagnetronControler/design.sv
module MagnetronControl(
  input start,
  input stop,
  input clear,
  input door_closed,
  input timer_done,
  output Enabler);
  
  reg Enabler;

  always @(*)
    begin
      if(stop)
        Enabler = 0;
      else if(clear)
        Enabler = 0;
      else if(timer_done)
        Enabler = 0;
      else if(~door_closed)
        Enabler = 0;
      else if(start)
		Enabler = 1;
    end
endmodule

MagnetronControler/testbench.sv
module test;

  reg start, stop, clear, door_closed, timer_done;
  wire Enabler;
  
  MagnetronControl dut(start, stop, clear, door_closed, timer_done, Enabler);

  initial begin
    $dumpfile("MagnetronControl.vcd");
	$dumpvars(0, test);
    start = 1; stop = 0; clear = 0; door_closed = 1; timer_done = 0; #10; //start
	start = 0; stop = 0; clear = 0; door_closed = 1; timer_done = 0; #10; //keepsON
    start = 1; stop = 0; clear = 0; door_closed = 0; timer_done = 0; #10; //Doortest
    start = 0; stop = 0; clear = 0; door_closed = 0; timer_done = 0; #10; //Transiçã
    start = 1; stop = 0; clear = 0; door_closed = 1; timer_done = 0; #10; //start
    start = 0; stop = 1; clear = 0; door_closed = 1; timer_done = 0; #10; //stoptest
    start = 1; stop = 0; clear = 0; door_closed = 1; timer_done = 0; #10; //start
    start = 0; stop = 0; clear = 1; door_closed = 1; timer_done = 0; #10; //cleartes
    start = 1; stop = 0; clear = 0; door_closed = 1; timer_done = 0; #10; //start
    start = 0; stop = 0; clear = 0; door_closed = 1; timer_done = 1; #10; //timertes
 

  
  end
endmodule

MagnetronControler/MagnetronControl.vcd
$date
	Fri May  6 20:09:17 2022
$end
$version
	Icarus Verilog
$end
$timescale
	1s
$end
$scope module test $end
$var wire 1 ! Enabler $end
$var reg 1 " clear $end
$var reg 1 # door_closed $end
$var reg 1 $ start $end
$var reg 1 % stop $end
$var reg 1 & timer_done $end
$scope module dut $end
$var wire 1 ' clear $end
$var wire 1 ( door_closed $end
$var wire 1 ) start $end
$var wire 1 * stop $end
$var wire 1 + timer_done $end
$var reg 1 , Enabler $end
$upscope $end
$upscope $end
$enddefinitions $end
#0
$dumpvars
1,
0+
0*
1)
1(
0'
0&
0%
1$
1#
0"
1!
$end
#10
0$
0)
#20
0,
0!
0#
0(
1$
1)
#30
0$
0)
#40
1,
1!
1#
1(
1$
1)
#50
0,
0!
1%
1*
0$
0)
#60
1,
1!
0%
0*
1$
1)
#70
0,
0!
1"
1'
0$
0)
#80
1,
1!
0"
0'
1$
1)
#90
0,
0!
1&
1+
0$
0)
