encoder/mux.v
module mux(
    input wire sel, pgt, clk,
    output reg out
);

    always @(sel, posedge pgt, clk) begin
        if (sel == 0) begin
            out <= clk;
        end

        else begin
            out <= pgt;
        end
    end
endmodule

encoder/nrc_mod7.v
module counter_mod7(
    input clk, clear,

    output reg pgt
);

    integer count = 0;

    always @(posedge clk) begin
        if (clear == 0) begin
            count <= 0;
        end

        else if (count < 7) begin
            count <= count + 1;
        end

        if (count < 4) begin
            pgt <= 0;
        end
        
        else begin
            pgt <= 1;
        end
    end
endmodule

encoder/freq_div.v
module freq_div(
    input wire clock,
    output reg div_clk
);
  
  integer count = 0;
  
  always @(posedge clock) begin
      if(count != 100)
        begin
          div_clk = 0;
        end

      else
        begin
          count = 0;
          div_clk = 1;
        end
      
      count = count + 1;
  end
endmodule

encoder/priority_encoder/priority_encoder.v
module priority_encoder (
    input [9:0] keypad,
    input enablen,

    output reg [3:0] D,
    output reg validn
);

    always @(keypad, enablen) begin
        // O microondas está funcionando, logo não é possível pressionar nenhuma tecla
        if (enablen == 0) begin
            validn = 1;
        end

        else begin
            case (keypad)
                // 1
                10'b1000000000: begin
                    D = 4'b0001;
                    validn = 0;
                end

                // 2
                10'b0100000000: begin
                    D = 4'b0010;
                    validn = 0;
                end
                
                // 3
                10'b0010000000: begin
                    D = 4'b0011;
                    validn = 0;
                end
                
                // 4
                10'b0001000000: begin
                    D = 4'b0100;
                    validn = 0;
                end

                // 5
                10'b0000100000: begin
                    D = 4'b0101;
                    validn = 0;
                end

                // 6
                10'b0000010000: begin
                    D = 4'b0110;
                    validn = 0;
                end

                // 7
                10'b0000001000: begin
                    D = 4'b0111;
                    validn = 0;
                end

                // 8
                10'b1000000100: begin
                    D = 4'b1000;
                    validn = 0;
                end

                // 9
                10'b0000000010: begin
                    D = 4'b1001;
                    validn = 0;
                end

                // 0
                10'b0000000001: begin
                    D = 4'b0000;
                    validn = 0;
                end

                // Caso em que nenhuma tecla está sendo pressionada
                10'b0000000000: validn = 1;

                // Input inválido
                default: begin
                    validn = 1;
                end
            endcase
        end
    end
endmodule

encoder/encoder.v
module encoder(
    input [9:0] keypad,
    input clk, enablen,

    output wire [3:0] D,
    output wire pgt_1hz, loadn
);

    wire validn, div_clk, pgt;

    priority_encoder p_encoder (.keypad(keypad), .enablen(enablen), .D(D), .validn(validn));

    freq_div div (.clock(clk), .div_clk(div_clk));

    counter_mod7 counter (.clk(clk), .clear(validn), .pgt(pgt));

    mux mux1 (.sel(enablen), .pgt(pgt), .clk(div_clk), .out(pgt_1hz));

    assign loadn = validn;

endmodule

encoder/encoder_tb.v
`timescale 1ms/1ms

module encoder_tb;
    reg [9:0] keypad_tb;
    reg clk_tb, enablen_tb;

    wire [3:0] D_tb;
    wire pgt1_hz_tb, loadn_tb;

    encoder uut (
    .keypad(keypad_tb),
    .clk(clk_tb),
    .enablen(enablen_tb),
    .D(D_tb),
    .pgt_1hz(pgt1_hz_tb),
    .loadn(loadn_tb));

    initial begin 
        clk_tb = 0;

        forever begin
            #5 clk_tb = ~clk_tb;
        end 
    end

    initial
        begin

            $dumpfile("encoder.vcd");
            $dumpvars(0, encoder_tb);

            enablen_tb = 1;
            #5;
        
            keypad_tb = 10'b0000000000;
            #5;

            keypad_tb = 10'b1000000000;
            #100;

            keypad_tb = 10'b0000000000;
            #5;

            keypad_tb = 10'b0000000001;
            #100;

            keypad_tb = 10'b0000000000;
            #5;

            keypad_tb = 10'b0000001000;
            #100;

            keypad_tb = 10'b0000000000;
            #5;

            keypad_tb = 10'b1000000000;
            #100;

            keypad_tb = 10'b0000000000;
            #5;

            // Input inválido
            keypad_tb = 10'b1000010000;
            #100;

            // Testando o clock durante o funcionamento do microondas
            enablen_tb = 0;
            #2000;

            $finish;
        end
endmodule

encoder/encoder.vcd
$date
	Wed May 11 19:21:13 2022
$end
$version
	Icarus Verilog
$end
$timescale
	1ms
$end
$scope module encoder_tb $end
$var wire 1 ! pgt1_hz_tb $end
$var wire 1 " loadn_tb $end
$var wire 4 # D_tb [3:0] $end
$var reg 1 $ clk_tb $end
$var reg 1 % enablen_tb $end
$var reg 10 & keypad_tb [9:0] $end
$scope module uut $end
$var wire 1 $ clk $end
$var wire 1 % enablen $end
$var wire 10 ' keypad [9:0] $end
$var wire 1 " loadn $end
$var wire 1 ( validn $end
$var wire 1 ! pgt_1hz $end
$var wire 1 ) pgt $end
$var wire 1 * div_clk $end
$var wire 4 + D [3:0] $end
$scope module counter $end
$var wire 1 $ clk $end
$var wire 1 ( clear $end
$var reg 1 ) pgt $end
$var integer 32 , count [31:0] $end
$upscope $end
$scope module div $end
$var wire 1 $ clock $end
$var reg 1 * div_clk $end
$var integer 32 - count [31:0] $end
$upscope $end
$scope module mux1 $end
$var wire 1 * clk $end
$var wire 1 ) pgt $end
$var wire 1 % sel $end
$var reg 1 ! out $end
$upscope $end
$scope module p_encoder $end
$var wire 1 % enablen $end
$var wire 10 . keypad [9:0] $end
$var reg 4 / D [3:0] $end
$var reg 1 ( validn $end
$upscope $end
$upscope $end
$upscope $end
$enddefinitions $end
#0
$dumpvars
bx /
bx .
b0 -
b0 ,
bx +
x*
x)
1(
bx '
bx &
1%
0$
bx #
1"
x!
$end
#5
0!
b1 -
0*
0)
b1 ,
b0 &
b0 '
b0 .
1$
#10
0"
0(
b1 #
b1 +
b1 /
b1000000000 &
b1000000000 '
b1000000000 .
0$
#15
b10 ,
b10 -
1$
#20
0$
#25
b11 -
b11 ,
1$
#30
0$
#35
1!
1)
b100 ,
b100 -
1$
#40
0$
#45
0!
b101 -
0)
b101 ,
1$
#50
0$
#55
b110 ,
b110 -
1$
#60
0$
#65
b111 -
b111 ,
1$
#70
0$
#75
b1000 -
1$
#80
0$
#85
b1001 -
1$
#90
0$
#95
b1010 -
1$
#100
0$
#105
b1011 -
1$
#110
1"
1(
0$
b0 &
b0 '
b0 .
#115
b0 ,
b1100 -
0"
0(
b0 #
b0 +
b0 /
1$
b1 &
b1 '
b1 .
#120
0$
#125
b1101 -
b1 ,
1$
#130
0$
#135
b10 ,
b1110 -
1$
#140
0$
#145
b1111 -
b11 ,
1$
#150
0$
#155
1!
1)
b100 ,
b10000 -
1$
#160
0$
#165
0!
b10001 -
0)
b101 ,
1$
#170
0$
#175
b110 ,
b10010 -
1$
#180
0$
#185
b10011 -
b111 ,
1$
#190
0$
#195
b10100 -
1$
#200
0$
#205
b10101 -
1$
#210
0$
#215
b10110 -
1"
1(
1$
b0 &
b0 '
b0 .
#220
b0 ,
0"
0(
b111 #
b111 +
b111 /
0$
b1000 &
b1000 '
b1000 .
#225
b10111 -
b1 ,
1$
#230
0$
#235
b10 ,
b11000 -
1$
#240
0$
#245
b11001 -
b11 ,
1$
#250
0$
#255
1!
1)
b100 ,
b11010 -
1$
#260
0$
#265
0!
b11011 -
0)
b101 ,
1$
#270
0$
#275
b110 ,
b11100 -
1$
#280
0$
#285
b11101 -
b111 ,
1$
#290
0$
#295
b11110 -
1$
#300
0$
#305
b11111 -
1$
#310
0$
#315
b100000 -
1$
#320
1"
1(
0$
b0 &
b0 '
b0 .
#325
b0 ,
b100001 -
0"
0(
b1 #
b1 +
b1 /
1$
b1000000000 &
b1000000000 '
b1000000000 .
#330
0$
#335
b1 ,
b100010 -
1$
#340
0$
#345
b100011 -
b10 ,
1$
#350
0$
#355
b11 ,
b100100 -
1$
#360
0$
#365
1!
b100101 -
1)
b100 ,
1$
#370
0$
#375
0!
0)
b101 ,
b100110 -
1$
#380
0$
#385
b100111 -
b110 ,
1$
#390
0$
#395
b111 ,
b101000 -
1$
#400
0$
#405
b101001 -
1$
#410
0$
#415
b101010 -
1$
#420
0$
#425
b101011 -
1"
1(
1$
b0 &
b0 '
b0 .
#430
0$
b1000010000 &
b1000010000 '
b1000010000 .
#435
b101100 -
1$
#440
0$
#445
b101101 -
1$
#450
0$
#455
b101110 -
1$
#460
0$
#465
b101111 -
1$
#470
0$
#475
b110000 -
1$
#480
0$
#485
b110001 -
1$
#490
0$
#495
b110010 -
1$
#500
0$
#505
b110011 -
1$
#510
0$
#515
b110100 -
1$
#520
0$
#525
b110101 -
1$
#530
0$
0%
#535
b110110 -
1$
#540
0$
#545
b110111 -
1$
#550
0$
#555
b111000 -
1$
#560
0$
#565
b111001 -
1$
#570
0$
#575
b111010 -
1$
#580
0$
#585
b111011 -
1$
#590
0$
#595
b111100 -
1$
#600
0$
#605
b111101 -
1$
#610
0$
#615
b111110 -
1$
#620
0$
#625
b111111 -
1$
#630
0$
#635
b1000000 -
1$
#640
0$
#645
b1000001 -
1$
#650
0$
#655
b1000010 -
1$
#660
0$
#665
b1000011 -
1$
#670
0$
#675
b1000100 -
1$
#680
0$
#685
b1000101 -
1$
#690
0$
#695
b1000110 -
1$
#700
0$
#705
b1000111 -
1$
#710
0$
#715
b1001000 -
1$
#720
0$
#725
b1001001 -
1$
#730
0$
#735
b1001010 -
1$
#740
0$
#745
b1001011 -
1$
#750
0$
#755
b1001100 -
1$
#760
0$
#765
b1001101 -
1$
#770
0$
#775
b1001110 -
1$
#780
0$
#785
b1001111 -
1$
#790
0$
#795
b1010000 -
1$
#800
0$
#805
b1010001 -
1$
#810
0$
#815
b1010010 -
1$
#820
0$
#825
b1010011 -
1$
#830
0$
#835
b1010100 -
1$
#840
0$
#845
b1010101 -
1$
#850
0$
#855
b1010110 -
1$
#860
0$
#865
b1010111 -
1$
#870
0$
#875
b1011000 -
1$
#880
0$
#885
b1011001 -
1$
#890
0$
#895
b1011010 -
1$
#900
0$
#905
b1011011 -
1$
#910
0$
#915
b1011100 -
1$
#920
0$
#925
b1011101 -
1$
#930
0$
#935
b1011110 -
1$
#940
0$
#945
b1011111 -
1$
#950
0$
#955
b1100000 -
1$
#960
0$
#965
b1100001 -
1$
#970
0$
#975
b1100010 -
1$
#980
0$
#985
b1100011 -
1$
#990
0$
#995
b1100100 -
1$
#1000
0$
#1005
1!
1*
b1 -
1$
#1010
0$
#1015
0!
b10 -
0*
1$
#1020
0$
#1025
b11 -
1$
#1030
0$
#1035
b100 -
1$
#1040
0$
#1045
b101 -
1$
#1050
0$
#1055
b110 -
1$
#1060
0$
#1065
b111 -
1$
#1070
0$
#1075
b1000 -
1$
#1080
0$
#1085
b1001 -
1$
#1090
0$
#1095
b1010 -
1$
#1100
0$
#1105
b1011 -
1$
#1110
0$
#1115
b1100 -
1$
#1120
0$
#1125
b1101 -
1$
#1130
0$
#1135
b1110 -
1$
#1140
0$
#1145
b1111 -
1$
#1150
0$
#1155
b10000 -
1$
#1160
0$
#1165
b10001 -
1$
#1170
0$
#1175
b10010 -
1$
#1180
0$
#1185
b10011 -
1$
#1190
0$
#1195
b10100 -
1$
#1200
0$
#1205
b10101 -
1$
#1210
0$
#1215
b10110 -
1$
#1220
0$
#1225
b10111 -
1$
#1230
0$
#1235
b11000 -
1$
#1240
0$
#1245
b11001 -
1$
#1250
0$
#1255
b11010 -
1$
#1260
0$
#1265
b11011 -
1$
#1270
0$
#1275
b11100 -
1$
#1280
0$
#1285
b11101 -
1$
#1290
0$
#1295
b11110 -
1$
#1300
0$
#1305
b11111 -
1$
#1310
0$
#1315
b100000 -
1$
#1320
0$
#1325
b100001 -
1$
#1330
0$
#1335
b100010 -
1$
#1340
0$
#1345
b100011 -
1$
#1350
0$
#1355
b100100 -
1$
#1360
0$
#1365
b100101 -
1$
#1370
0$
#1375
b100110 -
1$
#1380
0$
#1385
b100111 -
1$
#1390
0$
#1395
b101000 -
1$
#1400
0$
#1405
b101001 -
1$
#1410
0$
#1415
b101010 -
1$
#1420
0$
#1425
b101011 -
1$
#1430
0$
#1435
b101100 -
1$
#1440
0$
#1445
b101101 -
1$
#1450
0$
#1455
b101110 -
1$
#1460
0$
#1465
b101111 -
1$
#1470
0$
#1475
b110000 -
1$
#1480
0$
#1485
b110001 -
1$
#1490
0$
#1495
b110010 -
1$
#1500
0$
#1505
b110011 -
1$
#1510
0$
#1515
b110100 -
1$
#1520
0$
#1525
b110101 -
1$
#1530
0$
#1535
b110110 -
1$
#1540
0$
#1545
b110111 -
1$
#1550
0$
#1555
b111000 -
1$
#1560
0$
#1565
b111001 -
1$
#1570
0$
#1575
b111010 -
1$
#1580
0$
#1585
b111011 -
1$
#1590
0$
#1595
b111100 -
1$
#1600
0$
#1605
b111101 -
1$
#1610
0$
#1615
b111110 -
1$
#1620
0$
#1625
b111111 -
1$
#1630
0$
#1635
b1000000 -
1$
#1640
0$
#1645
b1000001 -
1$
#1650
0$
#1655
b1000010 -
1$
#1660
0$
#1665
b1000011 -
1$
#1670
0$
#1675
b1000100 -
1$
#1680
0$
#1685
b1000101 -
1$
#1690
0$
#1695
b1000110 -
1$
#1700
0$
#1705
b1000111 -
1$
#1710
0$
#1715
b1001000 -
1$
#1720
0$
#1725
b1001001 -
1$
#1730
0$
#1735
b1001010 -
1$
#1740
0$
#1745
b1001011 -
1$
#1750
0$
#1755
b1001100 -
1$
#1760
0$
#1765
b1001101 -
1$
#1770
0$
#1775
b1001110 -
1$
#1780
0$
#1785
b1001111 -
1$
#1790
0$
#1795
b1010000 -
1$
#1800
0$
#1805
b1010001 -
1$
#1810
0$
#1815
b1010010 -
1$
#1820
0$
#1825
b1010011 -
1$
#1830
0$
#1835
b1010100 -
1$
#1840
0$
#1845
b1010101 -
1$
#1850
0$
#1855
b1010110 -
1$
#1860
0$
#1865
b1010111 -
1$
#1870
0$
#1875
b1011000 -
1$
#1880
0$
#1885
b1011001 -
1$
#1890
0$
#1895
b1011010 -
1$
#1900
0$
#1905
b1011011 -
1$
#1910
0$
#1915
b1011100 -
1$
#1920
0$
#1925
b1011101 -
1$
#1930
0$
#1935
b1011110 -
1$
#1940
0$
#1945
b1011111 -
1$
#1950
0$
#1955
b1100000 -
1$
#1960
0$
#1965
b1100001 -
1$
#1970
0$
#1975
b1100010 -
1$
#1980
0$
#1985
b1100011 -
1$
#1990
0$
#1995
b1100100 -
1$
#2000
0$
#2005
1!
1*
b1 -
1$
#2010
0$
#2015
0!
b10 -
0*
1$
#2020
0$
#2025
b11 -
1$
#2030
0$
#2035
b100 -
1$
#2040
0$
#2045
b101 -
1$
#2050
0$
#2055
b110 -
1$
#2060
0$
#2065
b111 -
1$
#2070
0$
#2075
b1000 -
1$
#2080
0$
#2085
b1001 -
1$
#2090
0$
#2095
b1010 -
1$
#2100
0$
#2105
b1011 -
1$
#2110
0$
#2115
b1100 -
1$
#2120
0$
#2125
b1101 -
1$
#2130
0$
#2135
b1110 -
1$
#2140
0$
#2145
b1111 -
1$
#2150
0$
#2155
b10000 -
1$
#2160
0$
#2165
b10001 -
1$
#2170
0$
#2175
b10010 -
1$
#2180
0$
#2185
b10011 -
1$
#2190
0$
#2195
b10100 -
1$
#2200
0$
#2205
b10101 -
1$
#2210
0$
#2215
b10110 -
1$
#2220
0$
#2225
b10111 -
1$
#2230
0$
#2235
b11000 -
1$
#2240
0$
#2245
b11001 -
1$
#2250
0$
#2255
b11010 -
1$
#2260
0$
#2265
b11011 -
1$
#2270
0$
#2275
b11100 -
1$
#2280
0$
#2285
b11101 -
1$
#2290
0$
#2295
b11110 -
1$
#2300
0$
#2305
b11111 -
1$
#2310
0$
#2315
b100000 -
1$
#2320
0$
#2325
b100001 -
1$
#2330
0$
#2335
b100010 -
1$
#2340
0$
#2345
b100011 -
1$
#2350
0$
#2355
b100100 -
1$
#2360
0$
#2365
b100101 -
1$
#2370
0$
#2375
b100110 -
1$
#2380
0$
#2385
b100111 -
1$
#2390
0$
#2395
b101000 -
1$
#2400
0$
#2405
b101001 -
1$
#2410
0$
#2415
b101010 -
1$
#2420
0$
#2425
b101011 -
1$
#2430
0$
#2435
b101100 -
1$
#2440
0$
#2445
b101101 -
1$
#2450
0$
#2455
b101110 -
1$
#2460
0$
#2465
b101111 -
1$
#2470
0$
#2475
b110000 -
1$
#2480
0$
#2485
b110001 -
1$
#2490
0$
#2495
b110010 -
1$
#2500
0$
#2505
b110011 -
1$
#2510
0$
#2515
b110100 -
1$
#2520
0$
#2525
b110101 -
1$
